Workbook

Sheet Cover
A1: Aurelius Global Devices — Inventory Finance Control Book
A2: Synthetic enterprise training workbook | FY2026 Q3 close | Values are fictional | Version 1.0
A4: Workbook purpose | B4: Train an inventory add-in to identify, normalize, consolidate, value, and reconcile inventory from heterogeneous sources.
A5: Finance owner | B5: Global Inventory Controllership
A6: Reporting date | B6: 46234
A7: Functional currency | B7: USD
A8: Source systems | B8: SAP S/4HANA; Oracle Retail; NorthStar 3PL WMS; procurement tracker
A9: Complexity deliberately included | B9: Header aliases, SKU aliases, mixed UOM, currencies, duplicate rows, blank fields, stale counts, quarantined stock, transfers, and PO timing.
A10: Blue cells | B10: Source data / user inputs
A11: Green cells | B11: Calculated or reconciled outputs
A12: Important | B12: Do not treat every issue as an error: some exceptions are valid business states and require contextual handling.
A14: Suggested training tasks
A15: 1. Detect the source tables even though table names and headers differ.
A16: 2. Map aliases to canonical SKU and location identifiers.
A17: 3. Convert cases to eaches and local currency to USD without double-counting.
A18: 4. Separate unrestricted, quality-hold, damaged, and in-transit inventory.
A19: 5. Reconcile source totals to the Consolidated and Checks tabs.
A20: 6. Explain exceptions without changing finance-controlled calculations.

Sheet Executive Summary
A1: Inventory Finance Executive Summary
A2: Management view | As of 2026-07-31 | USD and base units
A4: Gross Inventory Value | D4: ='Reserve Analysis'!C18 -> 863132.2
A5: Obsolescence Reserve | D5: ='Reserve Analysis'!I18 -> 185129.59
A6: Net Inventory Value | D6: ='Reserve Analysis'!J18 -> 678002.61
A7: Net Available Units | D7: =SUM(Consolidated!I5:I16) -> 17888
A8: Open PO Commitments | D8: =SUM('Open POs'!N5:N14) -> 262808.2
A9: Unmapped 3PL Units | D9: =Checks!B6 -> 25
A12: Category | B12: Gross Value USD | C12: Reserve USD | D12: Net Value USD
A13: Mobile | B13: =SUMIF(Consolidated!$C$5:$C$16,A13,Consolidated!$P$5:$P$16) -> 203754 | C13: =SUMIF(Consolidated!$C$5:$C$16,A13,'Reserve Analysis'!$I$5:$I$16) -> 35755.05 | D13: =B13-C13 -> 167998.95
A14: Computing | B14: =SUMIF(Consolidated!$C$5:$C$16,A14,Consolidated!$P$5:$P$16) -> 372955 | C14: =SUMIF(Consolidated!$C$5:$C$16,A14,'Reserve Analysis'!$I$5:$I$16) -> 37295.5 | D14: =B14-C14 -> 335659.5
A15: Audio | B15: =SUMIF(Consolidated!$C$5:$C$16,A15,Consolidated!$P$5:$P$16) -> 57562 | C15: =SUMIF(Consolidated!$C$5:$C$16,A15,'Reserve Analysis'!$I$5:$I$16) -> 5756.2 | D15: =B15-C15 -> 51805.8
A16: Smart Home | B16: =SUMIF(Consolidated!$C$5:$C$16,A16,Consolidated!$P$5:$P$16) -> 74216 | C16: =SUMIF(Consolidated!$C$5:$C$16,A16,'Reserve Analysis'!$I$5:$I$16) -> 10448.3 | D16: =B16-C16 -> 63767.7
A17: Accessories | B17: =SUMIF(Consolidated!$C$5:$C$16,A17,Consolidated!$P$5:$P$16) -> 98725.2 | C17: =SUMIF(Consolidated!$C$5:$C$16,A17,'Reserve Analysis'!$I$5:$I$16) -> 81894.54 | D17: =B17-C17 -> 16830.66
A18: Gaming | B18: =SUMIF(Consolidated!$C$5:$C$16,A18,Consolidated!$P$5:$P$16) -> 55920 | C18: =SUMIF(Consolidated!$C$5:$C$16,A18,'Reserve Analysis'!$I$5:$I$16) -> 13980 | D18: =B18-C18 -> 41940
A21: SKU | B21: Product | C21: Months Cover | D21: Gross Value USD | E21: Flag
A22: =Consolidated!A5 -> NX-1001 | B22: =Consolidated!B5 -> Nova X1 Smartphone 128GB | C22: =Consolidated!N5 -> 6.989011 | D22: =Consolidated!P5 -> 102531 | E22: =Consolidated!R5 -> Possible duplicate SAP row
A23: =Consolidated!A6 -> NX-1002 | B23: =Consolidated!B6 -> Nova X1 Smartphone 256GB | C23: =Consolidated!N6 -> 4.3275261 | D23: =Consolidated!P6 -> 101223 | E23: =Consolidated!R6 -> Review OK
A24: =Consolidated!A7 -> TB-2100 | B24: =Consolidated!B7 -> Atlas 11-inch Tablet | C24: =Consolidated!N7 -> 4.6507937 | D24: =Consolidated!P7 -> 91450 | E24: =Consolidated!R7 -> Review OK
A25: =Consolidated!A8 -> LT-3300 | B25: =Consolidated!B8 -> Pioneer 14 Pro Laptop | C25: =Consolidated!N8 -> 4.905016 | D25: =Consolidated!P8 -> 281505 | E25: =Consolidated!R8 -> Missing Oracle cost on one row
A26: =Consolidated!A9 -> AU-4100 | B26: =Consolidated!B9 -> Orbit ANC Headphones | C26: =Consolidated!N9 -> 4.2964286 | D26: =Consolidated!P9 -> 35518 | E26: =Consolidated!R9 -> Review OK

Sheet Header Dictionary
A1: Header & Field Dictionary
A2: Canonical meanings and real-world aliases across systems. A robust add-in should infer semantics, not rely on one exact label.
A4: Canonical Field | B4: SAP Alias | C4: Oracle Alias | D4: 3PL Alias | E4: PO / Transfer Alias | F4: Meaning / Rule
A5: SKU | B5: Material | C5: Item Number | D5: Client Item | E5: Item / Product Code | F5: Map aliases through Item Master; preserve leading zeros and punctuation.
A6: Location | B6: Plant + SLoc | C6: Org / Store | D6: Facility | E6: Ship-To / Destination | F6: Normalize facility codes; do not merge stores with DCs.
A7: On Hand | B7: Unrestricted Qty | C7: SOH Qty | D7: Available | E7: — | F7: Physical quantity available before reservations; may be cases or eaches.
A8: Reserved | B8: Blocked / Reserved | C8: Customer Reserve | D8: Allocated | E8: — | F8: Committed inventory not freely available.
A9: Quality Hold | B9: Quality Inspection | C9: Damaged Qty | D9: Hold Qty | E9: — | F9: Not orderable. Finance may still carry value subject to reserve policy.
A10: Unit of Measure | B10: Base UoM | C10: Selling UOM | D10: Qty UOM | E10: Order UOM | F10: Convert to EA with Item Master units-per-case.
A11: Unit Cost | B11: MAP | C11: Retail Cost | D11: Declared Cost | E11: PO Unit Price | F11: Convert local currency using the reporting-date FX table.
A12: As-of Date | B12: Snapshot Date | C12: Stocktake Date | D12: As Of | E12: Expected Receipt | F12: Dates can be timestamps, local dates, or text exports.
A13: Currency | B13: Company Code Currency | C13: Currency Code | D13: Curr | E13: PO Currency | F13: All consolidated values reported in USD.

Sheet Item Master
A1: Global Item Master
A2: Finance-controlled canonical SKU mapping and costing attributes. Alias values are pipe-delimited to mimic master-data extracts.
A4: Canonical SKU | B4: Product Description | C4: Category | D4: Stocking UOM | E4: Units per Case | F4: Std Cost USD | G4: List Price USD | H4: Velocity Class | I4: Monthly Obsolescence Rate | J4: Known Source Aliases | K4: Lifecycle Status
A5: NX-1001 | B5: Nova X1 Smartphone 128GB | C5: Mobile | D5: EA | E5: 1 | F5: 429 | G5: 699 | H5: A | I5: 0.015 | J5: NX1-128|1001-NX | K5: Active
A6: NX-1002 | B6: Nova X1 Smartphone 256GB | C6: Mobile | D6: EA | E6: 1 | F6: 489 | G6: 799 | H6: A | I6: 0.015 | J6: NX1-256|1002-NX | K6: Active
A7: TB-2100 | B7: Atlas 11-inch Tablet | C7: Computing | D7: EA | E7: 1 | F7: 310 | G7: 499 | H7: A | I7: 0.012 | J7: ATLAS11|2100-TB | K7: Active
A8: LT-3300 | B8: Pioneer 14 Pro Laptop | C8: Computing | D8: EA | E8: 1 | F8: 735 | G8: 1199 | H8: A | I8: 0.01 | J8: PNR14|3300-LT | K8: Active
A9: AU-4100 | B9: Orbit ANC Headphones | C9: Audio | D9: EA | E9: 1 | F9: 86 | G9: 179 | H9: A | I9: 0.02 | J9: ORBIT-ANC|4100-AU | K9: Active
A10: AU-4200 | B10: Pulse Wireless Earbuds | C10: Audio | D10: EA | E10: 1 | F10: 44 | G10: 99 | H10: A | I10: 0.02 | J10: PULSE-BUDS|4200-AU | K10: Active
A11: HM-5100 | B11: Halo Smart Speaker | C11: Smart Home | D11: EA | E11: 1 | F11: 57 | G11: 129 | H11: B | I11: 0.025 | J11: HALO-SPK|5100-HM | K11: Phase Out
A12: HM-5200 | B12: Sentinel Video Doorbell | C12: Smart Home | D12: EA | E12: 1 | F12: 71 | G12: 159 | H12: A | I12: 0.018 | J12: SENT-DB|5200-HM | K12: Active
A13: AC-6100 | B13: 65W USB-C Power Adapter | C13: Accessories | D13: CS | E13: 12 | F13: 14 | G13: 39 | H13: A | I13: 0.03 | J13: USB65W|6100-AC | K13: Active
A14: AC-6200 | B14: Braided USB-C Cable 2m | C14: Accessories | D14: CS | E14: 24 | F14: 4.2 | G14: 19 | H14: B | I14: 0.04 | J14: CBL2M|6200-AC | K14: End of Life
A15: GM-7100 | B15: Vector Mechanical Keyboard | C15: Gaming | D15: EA | E15: 1 | F15: 63 | G15: 139 | H15: B | I15: 0.022 | J15: VECTOR-KB|7100-GM | K15: Active
A16: GM-7200 | B16: Photon Gaming Mouse | C16: Gaming | D16: EA | E16: 1 | F16: 31 | G16: 79 | H16: A | I16: 0.025 | J16: PHOTON-MSE|7200-GM | K16: Active

Sheet SAP DC Stock
A1: SAP S/4HANA Distribution Center Snapshot
A2: Raw MB52-style extract. Note SAP-specific headers, storage locations, blocked stock, and a repeated material/location batch.
A4: Material | B4: Plant | C4: SLoc | D4: Unrestricted Qty | E4: Blocked / Reserved | F4: Base UoM | G4: MAP | H4: Company Code Currency | I4: Snapshot Date | J4: Batch | K4: Stock Type | L4: Canonical SKU Helper | M4: Normalized Location | N4: Base Units Helper | O4: Extended Value USD Helper
A5: NX-1001 | B5: US01 | C5: 0002-QI | D5: 35 | E5: 8 | F5: EA | G5: 429 | H5: USD | I5: 46234 | J5: B260700 | K5: QI | L5: NX-1001 | M5: US01-0002-QI | N5: =D5*IF(F5="CS",VLOOKUP(L5,'Item Master'!$A$5:$E$16,5,FALSE),1) -> 35 | O5: =N5*G5*VLOOKUP(H5,'FX Rates'!$A$5:$B$8,2,FALSE) -> 15015
A6: NX-1002 | B6: US02 | C6: 0001 | D6: 72 | E6: 0 | F6: EA | G6: 489 | H6: USD | I6: 46234 | J6: B260701 | K6: UNRESTRICTED | L6: NX-1002 | M6: US02-0001 | N6: =D6*IF(F6="CS",VLOOKUP(L6,'Item Master'!$A$5:$E$16,5,FALSE),1) -> 72 | O6: =N6*G6*VLOOKUP(H6,'FX Rates'!$A$5:$B$8,2,FALSE) -> 35208
A7: TB-2100 | B7: CA01 | C7: 0001 | D7: 109 | E7: 0 | F7: EA | G7: 425.82418 | H7: CAD | I7: 46234 | J7: B260702 | K7: UNRESTRICTED | L7: TB-2100 | M7: CA01-0001 | N7: =D7*IF(F7="CS",VLOOKUP(L7,'Item Master'!$A$5:$E$16,5,FALSE),1) -> 109 | O7: =N7*G7*VLOOKUP(H7,'FX Rates'!$A$5:$B$8,2,FALSE) -> 33790
A8: LT-3300 | B8: US01 | C8: 0001 | D8: 146 | E8: 0 | F8: EA | G8: 735 | H8: USD | I8: 46234 | J8: B260703 | K8: UNRESTRICTED | L8: LT-3300 | M8: US01-0001 | N8: =D8*IF(F8="CS",VLOOKUP(L8,'Item Master'!$A$5:$E$16,5,FALSE),1) -> 146 | O8: =N8*G8*VLOOKUP(H8,'FX Rates'!$A$5:$B$8,2,FALSE) -> 107310
A9: AU-4100 | B9: US02 | C9: 0002-QI | D9: 183 | E9: 0 | F9: EA | G9: 86 | H9: USD | I9: 46234 | J9: B260704 | K9: QI | L9: AU-4100 | M9: US02-0002-QI | N9: =D9*IF(F9="CS",VLOOKUP(L9,'Item Master'!$A$5:$E$16,5,FALSE),1) -> 183 | O9: =N9*G9*VLOOKUP(H9,'FX Rates'!$A$5:$B$8,2,FALSE) -> 15738
A10: AU-4200 | B10: CA01 | C10: 0001 | D10: 220 | E10: 13 | F10: EA | G10: 60.43956 | H10: CAD | I10: 46234 | J10: B260705 | K10: UNRESTRICTED | L10: AU-4200 | M10: CA01-0001 | N10: =D10*IF(F10="CS",VLOOKUP(L10,'Item Master'!$A$5:$E$16,5,FALSE),1) -> 220 | O10: =N10*G10*VLOOKUP(H10,'FX Rates'!$A$5:$B$8,2,FALSE) -> 9680
A11: HM-5100 | B11: US01 | C11: 0001 | D11: 257 | E11: 0 | F11: EA | G11: 57 | H11: USD | I11: 46234 | J11: B260706 | K11: UNRESTRICTED | L11: HM-5100 | M11: US01-0001 | N11: =D11*IF(F11="CS",VLOOKUP(L11,'Item Master'!$A$5:$E$16,5,FALSE),1) -> 257 | O11: =N11*G11*VLOOKUP(H11,'FX Rates'!$A$5:$B$8,2,FALSE) -> 14649
A12: HM-5200 | B12: US02 | C12: 0001 | D12: 294 | E12: 0 | F12: EA | G12: 71 | H12: USD | I12: 46234 | J12: B260707 | K12: UNRESTRICTED | L12: HM-5200 | M12: US02-0001 | N12: =D12*IF(F12="CS",VLOOKUP(L12,'Item Master'!$A$5:$E$16,5,FALSE),1) -> 294 | O12: =N12*G12*VLOOKUP(H12,'FX Rates'!$A$5:$B$8,2,FALSE) -> 20874
A13: AC-6100 | B13: CA01 | C13: 0002-QI | D13: 331 | E13: 0 | F13: CS | G13: 19.230769 | H13: CAD | I13: 46234 | J13: B260708 | K13: QI | L13: AC-6100 | M13: CA01-0002-QI | N13: =D13*IF(F13="CS",VLOOKUP(L13,'Item Master'!$A$5:$E$16,5,FALSE),1) -> 3972 | O13: =N13*G13*VLOOKUP(H13,'FX Rates'!$A$5:$B$8,2,FALSE) -> 55608
A14: AC-6200 | B14: US01 | C14: 0001 | D14: 368 | E14: 0 | F14: CS | G14: 4.2 | H14: USD | I14: 46234 | J14: B260709 | K14: UNRESTRICTED | L14: AC-6200 | M14: US01-0001 | N14: =D14*IF(F14="CS",VLOOKUP(L14,'Item Master'!$A$5:$E$16,5,FALSE),1) -> 8832 | O14: =N14*G14*VLOOKUP(H14,'FX Rates'!$A$5:$B$8,2,FALSE) -> 37094.4
A15: GM-7100 | B15: US02 | C15: 0001 | D15: 405 | E15: 18 | F15: EA | G15: 63 | H15: USD | I15: 46234 | J15: B260710 | K15: UNRESTRICTED | L15: GM-7100 | M15: US02-0001 | N15: =D15*IF(F15="CS",VLOOKUP(L15,'Item Master'!$A$5:$E$16,5,FALSE),1) -> 405 | O15: =N15*G15*VLOOKUP(H15,'FX Rates'!$A$5:$B$8,2,FALSE) -> 25515
A16: GM-7200 | B16: CA01 | C16: 0001 | D16: 442 | E16: 0 | F16: EA | G16: 42.582418 | H16: CAD | I16: 46234 | J16: B260711 | K16: UNRESTRICTED | L16: GM-7200 | M16: CA01-0001 | N16: =D16*IF(F16="CS",VLOOKUP(L16,'Item Master'!$A$5:$E$16,5,FALSE),1) -> 442 | O16: =N16*G16*VLOOKUP(H16,'FX Rates'!$A$5:$B$8,2,FALSE) -> 13702
A17: NX-1001 | B17: US01 | C17: 0001 | D17: 120 | E17: 0 | F17: EA | G17: 429 | H17: USD | I17: 46234 | J17: B260799 | K17: UNRESTRICTED | L17: NX-1001 | M17: US01-0001 | N17: =D17 -> 120 | O17: =N17*G17 -> 51480

Sheet Oracle Store Inv
A1: Oracle Retail Store Inventory
A2: Store-level stock export with different aliases, stale count dates, local currency, damaged units, and one missing cost.
A4: Org / Store | B4: Item Number | C4: Item Description | D4: SOH Qty | E4: Customer Reserve | F4: Damaged Qty | G4: Selling UOM | H4: Retail Cost | I4: Currency Code | J4: Stocktake Date | K4: Posting Status | L4: Canonical SKU Helper | M4: Normalized Location | N4: Base Units Helper | O4: Extended Value USD Helper
A5: NYC-005 | B5: NX1-128 | C5: Nova X1 Smartphone 128GB | D5: 4 | E5: 2 | F5: 1 | G5: EA | H5: 429 | I5: USD | J5: 46231 | K5: CYCLE COUNT PENDING | L5: NX-1001 | M5: NYC-005 | N5: =D5 -> 4 | O5: =N5*H5*VLOOKUP(I5,'FX Rates'!$A$5:$B$8,2,FALSE) -> 1716
A6: CHI-014 | B6: NX-1002 | C6: Nova X1 Smartphone 256GB | D6: 15 | E6: 0 | F6: 0 | G6: EA | H6: 489 | I6: USD | J6: 46234 | K6: POSTED | L6: NX-1002 | M6: CHI-014 | N6: =D6 -> 15 | O6: =N6*H6*VLOOKUP(I6,'FX Rates'!$A$5:$B$8,2,FALSE) -> 7335
A7: DAL-022 | B7: TB-2100 | C7: Atlas 11-inch Tablet | D7: 26 | E7: 0 | F7: 0 | G7: EA | H7: 310 | I7: USD | J7: 46234 | K7: POSTED | L7: TB-2100 | M7: DAL-022 | N7: =D7 -> 26 | O7: =N7*H7*VLOOKUP(I7,'FX Rates'!$A$5:$B$8,2,FALSE) -> 8060
A8: TOR-031 | B8: PNR14 | C8: Pioneer 14 Pro Laptop | D8: 37 | E8: 0 | F8: 0 | G8: EA | H8: 1009.6154 | I8: CAD | J8: 46234 | K8: POSTED | L8: LT-3300 | M8: TOR-031 | N8: =D8 -> 37 | O8: =N8*H8*VLOOKUP(I8,'FX Rates'!$A$5:$B$8,2,FALSE) -> 27195
A9: NYC-005 | B9: AU-4100 | C9: Orbit ANC Headphones | D9: 48 | E9: 0 | F9: 0 | G9: EA | H9: 86 | I9: USD | J9: 46234 | K9: POSTED | L9: AU-4100 | M9: NYC-005 | N9: =D9 -> 48 | O9: =N9*H9*VLOOKUP(I9,'FX Rates'!$A$5:$B$8,2,FALSE) -> 4128
A10: CHI-014 | B10: AU-4200 | C10: Pulse Wireless Earbuds | D10: 59 | E10: 0 | F10: 0 | G10: EA | H10: 44 | I10: USD | J10: 46234 | K10: POSTED | L10: AU-4200 | M10: CHI-014 | N10: =D10 -> 59 | O10: =N10*H10*VLOOKUP(I10,'FX Rates'!$A$5:$B$8,2,FALSE) -> 2596
A11: DAL-022 | B11: HALO-SPK | C11: Halo Smart Speaker | D11: 12 | E11: 0 | F11: 0 | G11: EA | H11: 57 | I11: USD | J11: 46234 | K11: POSTED | L11: HM-5100 | M11: DAL-022 | N11: =D11 -> 12 | O11: =N11*H11*VLOOKUP(I11,'FX Rates'!$A$5:$B$8,2,FALSE) -> 684
A12: TOR-031 | B12: HM-5200 | C12: Sentinel Video Doorbell | D12: 23 | E12: 2 | F12: 0 | G12: EA | H12: 97.527473 | I12: CAD | J12: 46234 | K12: POSTED | L12: HM-5200 | M12: TOR-031 | N12: =D12 -> 23 | O12: =N12*H12*VLOOKUP(I12,'FX Rates'!$A$5:$B$8,2,FALSE) -> 1633
A13: NYC-005 | B13: AC-6100 | C13: 65W USB-C Power Adapter | D13: 34 | E13: 0 | F13: 0 | G13: EA | H13: 14 | I13: USD | J13: 46231 | K13: CYCLE COUNT PENDING | L13: AC-6100 | M13: NYC-005 | N13: =D13 -> 34 | O13: =N13*H13*VLOOKUP(I13,'FX Rates'!$A$5:$B$8,2,FALSE) -> 476
A14: CHI-014 | B14: CBL2M | C14: Braided USB-C Cable 2m | D14: 45 | E14: 0 | F14: 1 | G14: EA | H14: 4.2 | I14: USD | J14: 46234 | K14: POSTED | L14: AC-6200 | M14: CHI-014 | N14: =D14 -> 45 | O14: =N14*H14*VLOOKUP(I14,'FX Rates'!$A$5:$B$8,2,FALSE) -> 189
A15: DAL-022 | B15: GM-7100 | C15: Vector Mechanical Keyboard | D15: 56 | E15: 0 | F15: 0 | G15: EA | H15: 63 | I15: USD | J15: 46234 | K15: POSTED | L15: GM-7100 | M15: DAL-022 | N15: =D15 -> 56 | O15: =N15*H15*VLOOKUP(I15,'FX Rates'!$A$5:$B$8,2,FALSE) -> 3528
A16: TOR-031 | B16: GM-7200 | C16: Photon Gaming Mouse | D16: 9 | E16: 0 | F16: 0 | G16: EA | I16: CAD | J16: 46234 | K16: POSTED | L16: GM-7200 | M16: TOR-031 | N16: =D16 -> 9 | O16: =N16*H16*VLOOKUP(I16,'FX Rates'!$A$5:$B$8,2,FALSE) -> 0
A17: NYC-005 | B17: NX1-128 | C17: Nova X1 Smartphone 128GB | D17: 20 | E17: 0 | F17: 0 | G17: EA | H17: 429 | I17: USD | J17: 46234 | K17: POSTED | L17: NX-1001 | M17: NYC-005 | N17: =D17 -> 20 | O17: =N17*H17*VLOOKUP(I17,'FX Rates'!$A$5:$B$8,2,FALSE) -> 8580
A18: CHI-014 | B18: NX-1002 | C18: Nova X1 Smartphone 256GB | D18: 31 | E18: 0 | F18: 0 | G18: EA | H18: 489 | I18: USD | J18: 46234 | K18: POSTED | L18: NX-1002 | M18: CHI-014 | N18: =D18 -> 31 | O18: =N18*H18*VLOOKUP(I18,'FX Rates'!$A$5:$B$8,2,FALSE) -> 15159
A19: DAL-022 | B19: TB-2100 | C19: Atlas 11-inch Tablet | D19: 42 | E19: 2 | F19: 0 | G19: EA | H19: 310 | I19: USD | J19: 46234 | K19: POSTED | L19: TB-2100 | M19: DAL-022 | N19: =D19 -> 42 | O19: =N19*H19*VLOOKUP(I19,'FX Rates'!$A$5:$B$8,2,FALSE) -> 13020
A20: TOR-031 | B20: PNR14 | C20: Pioneer 14 Pro Laptop | D20: 53 | E20: 0 | F20: 0 | G20: EA | H20: 1009.6154 | I20: CAD | J20: 46234 | K20: POSTED | L20: LT-3300 | M20: TOR-031 | N20: =D20 -> 53 | O20: =N20*H20*VLOOKUP(I20,'FX Rates'!$A$5:$B$8,2,FALSE) -> 38955
A21: NYC-005 | B21: AU-4100 | C21: Orbit ANC Headphones | D21: 6 | E21: 0 | F21: 0 | G21: EA | H21: 86 | I21: USD | J21: 46231 | K21: CYCLE COUNT PENDING | L21: AU-4100 | M21: NYC-005 | N21: =D21 -> 6 | O21: =N21*H21*VLOOKUP(I21,'FX Rates'!$A$5:$B$8,2,FALSE) -> 516
A22: CHI-014 | B22: AU-4200 | C22: Pulse Wireless Earbuds | D22: 17 | E22: 0 | F22: 0 | G22: EA | H22: 44 | I22: USD | J22: 46234 | K22: POSTED | L22: AU-4200 | M22: CHI-014 | N22: =D22 -> 17 | O22: =N22*H22*VLOOKUP(I22,'FX Rates'!$A$5:$B$8,2,FALSE) -> 748
A23: DAL-022 | B23: HALO-SPK | C23: Halo Smart Speaker | D23: 28 | E23: 0 | F23: 1 | G23: EA | H23: 57 | I23: USD | J23: 46234 | K23: POSTED | L23: HM-5100 | M23: DAL-022 | N23: =D23 -> 28 | O23: =N23*H23*VLOOKUP(I23,'FX Rates'!$A$5:$B$8,2,FALSE) -> 1596
A24: TOR-031 | B24: HM-5200 | C24: Sentinel Video Doorbell | D24: 39 | E24: 0 | F24: 0 | G24: EA | H24: 97.527473 | I24: CAD | J24: 46234 | K24: POSTED | L24: HM-5200 | M24: TOR-031 | N24: =D24 -> 39 | O24: =N24*H24*VLOOKUP(I24,'FX Rates'!$A$5:$B$8,2,FALSE) -> 2769
A25: NYC-005 | B25: AC-6100 | C25: 65W USB-C Power Adapter | D25: 50 | E25: 0 | F25: 0 | G25: EA | H25: 14 | I25: USD | J25: 46234 | K25: POSTED | L25: AC-6100 | M25: NYC-005 | N25: =D25 -> 50 | O25: =N25*H25*VLOOKUP(I25,'FX Rates'!$A$5:$B$8,2,FALSE) -> 700
A26: CHI-014 | B26: CBL2M | C26: Braided USB-C Cable 2m | D26: 61 | E26: 2 | F26: 0 | G26: EA | H26: 4.2 | I26: USD | J26: 46234 | K26: POSTED | L26: AC-6200 | M26: CHI-014 | N26: =D26 -> 61 | O26: =N26*H26*VLOOKUP(I26,'FX Rates'!$A$5:$B$8,2,FALSE) -> 256.2
A27: DAL-022 | B27: GM-7100 | C27: Vector Mechanical Keyboard | D27: 14 | E27: 0 | F27: 0 | G27: EA | H27: 63 | I27: USD | J27: 46234 | K27: POSTED | L27: GM-7100 | M27: DAL-022 | N27: =D27 -> 14 | O27: =N27*H27*VLOOKUP(I27,'FX Rates'!$A$5:$B$8,2,FALSE) -> 882
A28: TOR-031 | B28: GM-7200 | C28: Photon Gaming Mouse | D28: 25 | E28: 0 | F28: 0 | G28: EA | H28: 42.582418 | I28: CAD | J28: 46234 | K28: POSTED | L28: GM-7200 | M28: TOR-031 | N28: =D28 -> 25 | O28: =N28*H28*VLOOKUP(I28,'FX Rates'!$A$5:$B$8,2,FALSE) -> 775

Sheet 3PL Warehouse Feed
A1: NorthStar 3PL Warehouse Feed
A2: Partner WMS feed with yet another header vocabulary, text timestamps, case quantities, allocations, and an unmapped vendor SKU.
A4: Facility | B4: Client Item | C4: Available | D4: Allocated | E4: Hold Qty | F4: Qty UOM | G4: Declared Cost | H4: Curr | I4: As Of | J4: Inventory Status | K4: Canonical SKU Helper | L4: Normalized Location | M4: Base Units Helper | N4: Extended Value USD Helper
A5: NJ-3PL | B5: NX-1001 | C5: 60 | D5: 12 | E5: 4 | F5: EA | G5: 429 | H5: USD | I5: 2026/07/31 23:00 ET | J5: AVAILABLE | K5: NX-1001 | L5: NJ-3PL | M5: =C5*IF(F5="CS",VLOOKUP(K5,'Item Master'!$A$5:$E$16,5,FALSE),1) -> 60 | N5: =M5*G5 -> 25740
A6: NJ-3PL | B6: 1002-NX | C6: 89 | D6: 0 | E6: 0 | F6: EA | G6: 489 | H6: USD | I6: 2026/07/31 23:00 ET | J6: AVAILABLE | K6: NX-1002 | L6: NJ-3PL | M6: =C6*IF(F6="CS",VLOOKUP(K6,'Item Master'!$A$5:$E$16,5,FALSE),1) -> 89 | N6: =M6*G6 -> 43521
A7: NJ-3PL | B7: TB-2100 | C7: 118 | D7: 0 | E7: 0 | F7: EA | G7: 310 | H7: USD | I7: 2026/07/31 23:00 ET | J7: AVAILABLE | K7: TB-2100 | L7: NJ-3PL | M7: =C7*IF(F7="CS",VLOOKUP(K7,'Item Master'!$A$5:$E$16,5,FALSE),1) -> 118 | N7: =M7*G7 -> 36580
A8: NJ-3PL | B8: 3300-LT | C8: 147 | D8: 0 | E8: 0 | F8: EA | G8: 735 | H8: USD | I8: 2026/07/31 23:00 ET | J8: AVAILABLE | K8: LT-3300 | L8: NJ-3PL | M8: =C8*IF(F8="CS",VLOOKUP(K8,'Item Master'!$A$5:$E$16,5,FALSE),1) -> 147 | N8: =M8*G8 -> 108045
A9: NJ-3PL | B9: AU-4100 | C9: 176 | D9: 12 | E9: 0 | F9: EA | G9: 86 | H9: USD | I9: 2026/07/31 23:00 ET | J9: AVAILABLE | K9: AU-4100 | L9: NJ-3PL | M9: =C9*IF(F9="CS",VLOOKUP(K9,'Item Master'!$A$5:$E$16,5,FALSE),1) -> 176 | N9: =M9*G9 -> 15136
A10: NJ-3PL | B10: 4200-AU | C10: 205 | D10: 0 | E10: 0 | F10: EA | G10: 44 | H10: USD | I10: 2026/07/31 23:00 ET | J10: AVAILABLE | K10: AU-4200 | L10: NJ-3PL | M10: =C10*IF(F10="CS",VLOOKUP(K10,'Item Master'!$A$5:$E$16,5,FALSE),1) -> 205 | N10: =M10*G10 -> 9020
A11: NJ-3PL | B11: HM-5100 | C11: 234 | D11: 0 | E11: 4 | F11: EA | G11: 57 | H11: USD | I11: 2026/07/31 23:00 ET | J11: AVAILABLE | K11: HM-5100 | L11: NJ-3PL | M11: =C11*IF(F11="CS",VLOOKUP(K11,'Item Master'!$A$5:$E$16,5,FALSE),1) -> 234 | N11: =M11*G11 -> 13338
A12: NJ-3PL | B12: 5200-HM | C12: 263 | D12: 0 | E12: 0 | F12: EA | G12: 71 | H12: USD | I12: 2026/07/29 23:00 ET | J12: AVAILABLE | K12: HM-5200 | L12: NJ-3PL | M12: =C12*IF(F12="CS",VLOOKUP(K12,'Item Master'!$A$5:$E$16,5,FALSE),1) -> 263 | N12: =M12*G12 -> 18673
A13: NJ-3PL | B13: AC-6100 | C13: 16 | D13: 12 | E13: 0 | F13: CS | G13: 14 | H13: USD | I13: 2026/07/31 23:00 ET | J13: AVAILABLE | K13: AC-6100 | L13: NJ-3PL | M13: =C13*IF(F13="CS",VLOOKUP(K13,'Item Master'!$A$5:$E$16,5,FALSE),1) -> 192 | N13: =M13*G13 -> 2688
A14: NJ-3PL | B14: 6200-AC | C14: 17 | D14: 0 | E14: 0 | F14: CS | G14: 4.2 | H14: USD | I14: 2026/07/31 23:00 ET | J14: AVAILABLE | K14: AC-6200 | L14: NJ-3PL | M14: =C14*IF(F14="CS",VLOOKUP(K14,'Item Master'!$A$5:$E$16,5,FALSE),1) -> 408 | N14: =M14*G14 -> 1713.6
A15: NJ-3PL | B15: GM-7100 | C15: 110 | D15: 0 | E15: 0 | F15: EA | G15: 63 | H15: USD | I15: 2026/07/31 23:00 ET | J15: CLIENT HOLD | K15: GM-7100 | L15: NJ-3PL | M15: =C15*IF(F15="CS",VLOOKUP(K15,'Item Master'!$A$5:$E$16,5,FALSE),1) -> 110 | N15: =M15*G15 -> 6930
A16: NJ-3PL | B16: 7200-GM | C16: 139 | D16: 0 | E16: 0 | F16: EA | G16: 31 | H16: USD | I16: 2026/07/31 23:00 ET | J16: AVAILABLE | K16: GM-7200 | L16: NJ-3PL | M16: =C16*IF(F16="CS",VLOOKUP(K16,'Item Master'!$A$5:$E$16,5,FALSE),1) -> 139 | N16: =M16*G16 -> 4309
A17: NJ-3PL | B17: VEND-UNKNOWN-88 | C17: 25 | D17: 0 | E17: 0 | F17: EA | G17: 18 | H17: USD | I17: 2026/07/31 23:00 ET | J17: AVAILABLE | K17: UNMAPPED | L17: NJ-3PL | M17: =C17 -> 25 | N17: =M17*G17 -> 450

Sheet Open POs
A1: Open Purchase Orders
A2: Procurement tracker. Quantities may be cases or eaches; PO currency and expected receipt dates affect cash and availability.
A4: PO Number | B4: Vendor | C4: Item / Product Code | D4: Description | E4: Order Qty | F4: Order UOM | G4: PO Unit Price | H4: PO Currency | I4: Ship-To / Destination | J4: Expected Receipt | K4: PO Status | L4: Canonical SKU Helper | M4: Base Units Helper | N4: Open Commitment USD Helper
A5: 45820100 | B5: EuroTech GmbH | C5: NX-1001 | D5: Nova X1 Smartphone 128GB | E5: 80 | F5: EA | G5: 375.65674 | H5: EUR | I5: US01-0001 | J5: 46237 | K5: Open | L5: NX-1001 | M5: =E5*IF(F5="CS",VLOOKUP(L5,'Item Master'!$A$5:$E$16,5,FALSE),1) -> 80 | N5: =M5*G5*VLOOKUP(H5,'FX Rates'!$A$5:$B$8,2,FALSE) -> 34320
A6: 45820101 | B6: Pacific Components Ltd | C6: NX-1002 | D6: Nova X1 Smartphone 256GB | E6: 97 | F6: EA | G6: 489 | H6: USD | I6: NJ-3PL | J6: 46238 | K6: Open | L6: NX-1002 | M6: =E6*IF(F6="CS",VLOOKUP(L6,'Item Master'!$A$5:$E$16,5,FALSE),1) -> 97 | N6: =M6*G6*VLOOKUP(H6,'FX Rates'!$A$5:$B$8,2,FALSE) -> 47433
A7: 45820102 | B7: Pacific Components Ltd | C7: TB-2100 | D7: Atlas 11-inch Tablet | E7: 114 | F7: EA | G7: 310 | H7: USD | I7: NJ-3PL | J7: 46239 | K7: Open | L7: TB-2100 | M7: =E7*IF(F7="CS",VLOOKUP(L7,'Item Master'!$A$5:$E$16,5,FALSE),1) -> 114 | N7: =M7*G7*VLOOKUP(H7,'FX Rates'!$A$5:$B$8,2,FALSE) -> 35340
A8: 45820103 | B8: EuroTech GmbH | C8: LT-3300 | D8: Pioneer 14 Pro Laptop | E8: 131 | F8: EA | G8: 735 | H8: USD | I8: US01-0001 | J8: 46240 | K8: Open | L8: LT-3300 | M8: =E8*IF(F8="CS",VLOOKUP(L8,'Item Master'!$A$5:$E$16,5,FALSE),1) -> 131 | N8: =M8*G8*VLOOKUP(H8,'FX Rates'!$A$5:$B$8,2,FALSE) -> 96285
A9: 45820104 | B9: Pacific Components Ltd | C9: AU-4100 | D9: Orbit ANC Headphones | E9: 148 | F9: EA | G9: 75.30648 | H9: EUR | I9: NJ-3PL | J9: 46241 | K9: Quality Hold | L9: AU-4100 | M9: =E9*IF(F9="CS",VLOOKUP(L9,'Item Master'!$A$5:$E$16,5,FALSE),1) -> 148 | N9: =M9*G9*VLOOKUP(H9,'FX Rates'!$A$5:$B$8,2,FALSE) -> 12728
A10: 45820105 | B10: Pacific Components Ltd | C10: AU-4200 | D10: Pulse Wireless Earbuds | E10: 165 | F10: EA | G10: 44 | H10: USD | I10: NJ-3PL | J10: 46242 | K10: Open | L10: AU-4200 | M10: =E10*IF(F10="CS",VLOOKUP(L10,'Item Master'!$A$5:$E$16,5,FALSE),1) -> 165 | N10: =M10*G10*VLOOKUP(H10,'FX Rates'!$A$5:$B$8,2,FALSE) -> 7260
A11: 45820106 | B11: EuroTech GmbH | C11: HM-5100 | D11: Halo Smart Speaker | E11: 182 | F11: EA | G11: 57 | H11: USD | I11: US01-0001 | J11: 46243 | K11: Open | L11: HM-5100 | M11: =E11*IF(F11="CS",VLOOKUP(L11,'Item Master'!$A$5:$E$16,5,FALSE),1) -> 182 | N11: =M11*G11*VLOOKUP(H11,'FX Rates'!$A$5:$B$8,2,FALSE) -> 10374
A12: 45820107 | B12: Pacific Components Ltd | C12: HM-5200 | D12: Sentinel Video Doorbell | E12: 199 | F12: EA | G12: 71 | H12: USD | I12: NJ-3PL | J12: 46244 | K12: Past Due | L12: HM-5200 | M12: =E12*IF(F12="CS",VLOOKUP(L12,'Item Master'!$A$5:$E$16,5,FALSE),1) -> 199 | N12: =M12*G12*VLOOKUP(H12,'FX Rates'!$A$5:$B$8,2,FALSE) -> 14129
A13: 45820108 | B13: Pacific Components Ltd | C13: AC-6100 | D13: 65W USB-C Power Adapter | E13: 18 | F13: CS | G13: 12.259194 | H13: EUR | I13: NJ-3PL | J13: 46245 | K13: Open | L13: AC-6100 | M13: =E13*IF(F13="CS",VLOOKUP(L13,'Item Master'!$A$5:$E$16,5,FALSE),1) -> 216 | N13: =M13*G13*VLOOKUP(H13,'FX Rates'!$A$5:$B$8,2,FALSE) -> 3024
A14: 45820109 | B14: EuroTech GmbH | C14: AC-6200 | D14: Braided USB-C Cable 2m | E14: 19 | F14: CS | G14: 4.2 | H14: USD | I14: US01-0001 | J14: 46246 | K14: Open | L14: AC-6200 | M14: =E14*IF(F14="CS",VLOOKUP(L14,'Item Master'!$A$5:$E$16,5,FALSE),1) -> 456 | N14: =M14*G14*VLOOKUP(H14,'FX Rates'!$A$5:$B$8,2,FALSE) -> 1915.2

Sheet In-Transit
A1: Intercompany & Interlocation Transfers
A2: Goods shipped but not yet received. Ownership may remain with the shipping entity depending on incoterms.
A4: Transfer ID | B4: Product Code | C4: From Site | D4: Destination | E4: Ship Quantity | F4: UOM | G4: Shipped Date | H4: Expected Arrival | I4: Movement Status | J4: Canonical SKU Helper | K4: Base Units Helper | L4: Value USD Helper
A5: TR-260731 | B5: TB-2100 | C5: NJ-3PL | D5: NYC-005 | E5: 25 | F5: EA | G5: 46228 | H5: 46235 | I5: In Transit | J5: TB-2100 | K5: 25 | L5: 7750
A6: TR-260732 | B6: LT-3300 | C6: US02-0001 | D6: CHI-014 | E6: 34 | F6: EA | G6: 46229 | H6: 46236 | I6: In Transit | J6: LT-3300 | K6: 34 | L6: 24990
A7: TR-260733 | B7: AU-4100 | C7: NJ-3PL | D7: DAL-022 | E7: 43 | F7: EA | G7: 46230 | H7: 46237 | I7: In Transit | J7: AU-4100 | K7: 43 | L7: 3698
A8: TR-260734 | B8: AU-4200 | C8: US02-0001 | D8: TOR-031 | E8: 52 | F8: EA | G8: 46231 | H8: 46238 | I8: Customs Hold | J8: AU-4200 | K8: 52 | L8: 2288
A9: TR-260735 | B9: HM-5100 | C9: NJ-3PL | D9: NYC-005 | E9: 61 | F9: EA | G9: 46232 | H9: 46239 | I9: In Transit | J9: HM-5100 | K9: 61 | L9: 3477
A10: TR-260736 | B10: HM-5200 | C10: US02-0001 | D10: CHI-014 | E10: 70 | F10: EA | G10: 46233 | H10: 46235 | I10: In Transit | J10: HM-5200 | K10: 70 | L10: 4970
A11: TR-260737 | B11: AC-6100 | C11: NJ-3PL | D11: DAL-022 | E11: 79 | F11: EA | G11: 46234 | H11: 46236 | I11: Delayed | J11: AC-6100 | K11: 79 | L11: 1106
A12: TR-260738 | B12: AC-6200 | C12: US02-0001 | D12: TOR-031 | E12: 88 | F12: EA | G12: 46235 | H12: 46237 | I12: In Transit | J12: AC-6200 | K12: 88 | L12: 369.6

Sheet Sales History
A1: Trailing 12-Month Sales & Returns
A2: Monthly demand history by channel. Returns are negative and holidays/promotions create seasonality; this is suitable for forecasting tests.
A4: Fiscal Month End | B4: SKU / Style | C4: Sales Channel | D4: Gross Units | E4: Returns Units | F4: Avg Net Price USD | G4: Canonical SKU Helper | H4: Net Demand Units Helper
A5: 45928 | B5: NX-1001 | C5: DTC | D5: 28 | E5: -2 | F5: 699 | G5: NX-1001 | H5: =D5+E5 -> 26
A6: 45928 | B6: NX-1002 | C6: Retail | D6: 41 | E6: 0 | F6: 799 | G6: NX-1002 | H6: =D6+E6 -> 41
A7: 45928 | B7: TB-2100 | C7: Wholesale | D7: 54 | E7: 0 | F7: 499 | G7: TB-2100 | H7: =D7+E7 -> 54
A8: 45928 | B8: LT-3300 | C8: DTC | D8: 67 | E8: 0 | F8: 1199 | G8: LT-3300 | H8: =D8+E8 -> 67
A9: 45928 | B9: AU-4100 | C9: Retail | D9: 80 | E9: 0 | F9: 179 | G9: AU-4100 | H9: =D9+E9 -> 80
A10: 45928 | B10: AU-4200 | C10: Wholesale | D10: 93 | E10: 0 | F10: 99 | G10: AU-4200 | H10: =D10+E10 -> 93
A11: 45928 | B11: HM-5100 | C11: DTC | D11: 106 | E11: 0 | F11: 129 | G11: HM-5100 | H11: =D11+E11 -> 106
A12: 45928 | B12: HM-5200 | C12: Retail | D12: 119 | E12: 0 | F12: 159 | G12: HM-5200 | H12: =D12+E12 -> 119
A13: 45928 | B13: AC-6100 | C13: Wholesale | D13: 37 | E13: 0 | F13: 39 | G13: AC-6100 | H13: =D13+E13 -> 37
A14: 45928 | B14: AC-6200 | C14: DTC | D14: 50 | E14: 0 | F14: 19 | G14: AC-6200 | H14: =D14+E14 -> 50
A15: 45928 | B15: GM-7100 | C15: Retail | D15: 63 | E15: 0 | F15: 139 | G15: GM-7100 | H15: =D15+E15 -> 63
A16: 45928 | B16: GM-7200 | C16: Wholesale | D16: 76 | E16: -6 | F16: 79 | G16: GM-7200 | H16: =D16+E16 -> 70
... A148: 46262 | B148: GM-7200 | C148: Wholesale | D148: 137 | E148: -11 | F148: 79 | G148: GM-7200 | H148: =D148+E148 -> 126

Sheet FX Rates
A1: Reporting-Date FX Rates
A2: USD per one unit of source currency, approved for the 2026-07-31 close.
A4: Currency | B4: USD per LC | C4: Rate Date | D4: Rate Type | E4: Owner
A5: USD | B5: 1 | C5: 46234 | D5: Identity | E5: Treasury
A6: CAD | B6: 0.728 | C6: 46234 | D6: Month-end spot | E6: Treasury
A7: EUR | B7: 1.142 | C7: 46234 | D7: Month-end spot | E7: Treasury
A8: GBP | B8: 1.334 | C8: 46234 | D8: Month-end spot | E8: Treasury

Sheet Consolidated
A1: Consolidated Inventory Position
A2: Canonical SKU view in base units and USD. Formula-driven from the heterogeneous source tabs; does not include unmapped rows.
A4: Canonical SKU | B4: Product | C4: Category | D4: SAP Base Units | E4: Oracle Base Units | F4: 3PL Base Units | G4: Gross On Hand | H4: Restricted / Damaged | I4: Net Available | J4: In Transit | K4: Open PO Units | L4: TTM Net Demand | M4: Avg Monthly Demand | N4: Months Cover | O4: Std Cost USD | P4: Gross Value USD | Q4: Lifecycle | R4: Data Quality Flag
A5: NX-1001 | B5: Nova X1 Smartphone 128GB | C5: Mobile | D5: =SUMIF('SAP DC Stock'!$L$5:$L$17,A5,'SAP DC Stock'!$N$5:$N$17) -> 155 | E5: =SUMIF('Oracle Store Inv'!$L$5:$L$28,A5,'Oracle Store Inv'!$N$5:$N$28) -> 24 | F5: =SUMIF('3PL Warehouse Feed'!$K$5:$K$17,A5,'3PL Warehouse Feed'!$M$5:$M$17) -> 60 | G5: =SUM(D5:F5) -> 239 | H5: =SUMIF('SAP DC Stock'!$L$5:$L$17,A5,'SAP DC Stock'!$E$5:$E$17)+SUMIF('Oracle Store Inv'!$L$5:$L$28,A5,'Oracle Store Inv'!$E$5:$E$28)+SUMIF('Oracle Store Inv'!$L$5:$L$28,A5,'Oracle Store Inv'!$F$5:$F$28)+SUMIF('3PL Warehouse Feed'!$K$5:$K$17,A5,'3PL Warehouse Feed'!$D$5:$D$17)+SUMIF('3PL Warehouse Feed'!$K$5:$K$17,A5,'3PL Warehouse Feed'!$E$5:$E$17) -> 27 | I5: =MAX(0,G5-H5) -> 212 | J5: =SUMIF('In-Transit'!$J$5:$J$12,A5,'In-Transit'!$K$5:$K$12) -> 0 | K5: =SUMIF('Open POs'!$L$5:$L$14,A5,'Open POs'!$M$5:$M$14) -> 80 | L5: =SUMIF('Sales History'!$G$5:$G$148,A5,'Sales History'!$H$5:$H$148) -> 364 | M5: =L5/12 -> 30.333333 | N5: =IF(M5=0,0,I5/M5) -> 6.989011 | O5: =VLOOKUP(A5,'Item Master'!$A$5:$K$16,6,FALSE) -> 429 | P5: =G5*O5 -> 102531 | Q5: =VLOOKUP(A5,'Item Master'!$A$5:$K$16,11,FALSE) -> Active | R5: =IF(A5="NX-1001","Possible duplicate SAP row",IF(A5="LT-3300","Missing Oracle cost on one row",IF(N5>6,"Excess cover",IF(N5<1,"Stockout risk","Review OK")))) -> Possible duplicate SAP row
A6: NX-1002 | B6: Nova X1 Smartphone 256GB | C6: Mobile | D6: =SUMIF('SAP DC Stock'!$L$5:$L$17,A6,'SAP DC Stock'!$N$5:$N$17) -> 72 | E6: =SUMIF('Oracle Store Inv'!$L$5:$L$28,A6,'Oracle Store Inv'!$N$5:$N$28) -> 46 | F6: =SUMIF('3PL Warehouse Feed'!$K$5:$K$17,A6,'3PL Warehouse Feed'!$M$5:$M$17) -> 89 | G6: =SUM(D6:F6) -> 207 | H6: =SUMIF('SAP DC Stock'!$L$5:$L$17,A6,'SAP DC Stock'!$E$5:$E$17)+SUMIF('Oracle Store Inv'!$L$5:$L$28,A6,'Oracle Store Inv'!$E$5:$E$28)+SUMIF('Oracle Store Inv'!$L$5:$L$28,A6,'Oracle Store Inv'!$F$5:$F$28)+SUMIF('3PL Warehouse Feed'!$K$5:$K$17,A6,'3PL Warehouse Feed'!$D$5:$D$17)+SUMIF('3PL Warehouse Feed'!$K$5:$K$17,A6,'3PL Warehouse Feed'!$E$5:$E$17) -> 0 | I6: =MAX(0,G6-H6) -> 207 | J6: =SUMIF('In-Transit'!$J$5:$J$12,A6,'In-Transit'!$K$5:$K$12) -> 0 | K6: =SUMIF('Open POs'!$L$5:$L$14,A6,'Open POs'!$M$5:$M$14) -> 97 | L6: =SUMIF('Sales History'!$G$5:$G$148,A6,'Sales History'!$H$5:$H$148) -> 574 | M6: =L6/12 -> 47.833333 | N6: =IF(M6=0,0,I6/M6) -> 4.3275261 | O6: =VLOOKUP(A6,'Item Master'!$A$5:$K$16,6,FALSE) -> 489 | P6: =G6*O6 -> 101223 | Q6: =VLOOKUP(A6,'Item Master'!$A$5:$K$16,11,FALSE) -> Active | R6: =IF(A6="NX-1001","Possible duplicate SAP row",IF(A6="LT-3300","Missing Oracle cost on one row",IF(N6>6,"Excess cover",IF(N6<1,"Stockout risk","Review OK")))) -> Review OK
A7: TB-2100 | B7: Atlas 11-inch Tablet | C7: Computing | D7: =SUMIF('SAP DC Stock'!$L$5:$L$17,A7,'SAP DC Stock'!$N$5:$N$17) -> 109 | E7: =SUMIF('Oracle Store Inv'!$L$5:$L$28,A7,'Oracle Store Inv'!$N$5:$N$28) -> 68 | F7: =SUMIF('3PL Warehouse Feed'!$K$5:$K$17,A7,'3PL Warehouse Feed'!$M$5:$M$17) -> 118 | G7: =SUM(D7:F7) -> 295 | H7: =SUMIF('SAP DC Stock'!$L$5:$L$17,A7,'SAP DC Stock'!$E$5:$E$17)+SUMIF('Oracle Store Inv'!$L$5:$L$28,A7,'Oracle Store Inv'!$E$5:$E$28)+SUMIF('Oracle Store Inv'!$L$5:$L$28,A7,'Oracle Store Inv'!$F$5:$F$28)+SUMIF('3PL Warehouse Feed'!$K$5:$K$17,A7,'3PL Warehouse Feed'!$D$5:$D$17)+SUMIF('3PL Warehouse Feed'!$K$5:$K$17,A7,'3PL Warehouse Feed'!$E$5:$E$17) -> 2 | I7: =MAX(0,G7-H7) -> 293 | J7: =SUMIF('In-Transit'!$J$5:$J$12,A7,'In-Transit'!$K$5:$K$12) -> 25 | K7: =SUMIF('Open POs'!$L$5:$L$14,A7,'Open POs'!$M$5:$M$14) -> 114 | L7: =SUMIF('Sales History'!$G$5:$G$148,A7,'Sales History'!$H$5:$H$148) -> 756 | M7: =L7/12 -> 63 | N7: =IF(M7=0,0,I7/M7) -> 4.6507937 | O7: =VLOOKUP(A7,'Item Master'!$A$5:$K$16,6,FALSE) -> 310 | P7: =G7*O7 -> 91450 | Q7: =VLOOKUP(A7,'Item Master'!$A$5:$K$16,11,FALSE) -> Active | R7: =IF(A7="NX-1001","Possible duplicate SAP row",IF(A7="LT-3300","Missing Oracle cost on one row",IF(N7>6,"Excess cover",IF(N7<1,"Stockout risk","Review OK")))) -> Review OK
A8: LT-3300 | B8: Pioneer 14 Pro Laptop | C8: Computing | D8: =SUMIF('SAP DC Stock'!$L$5:$L$17,A8,'SAP DC Stock'!$N$5:$N$17) -> 146 | E8: =SUMIF('Oracle Store Inv'!$L$5:$L$28,A8,'Oracle Store Inv'!$N$5:$N$28) -> 90 | F8: =SUMIF('3PL Warehouse Feed'!$K$5:$K$17,A8,'3PL Warehouse Feed'!$M$5:$M$17) -> 147 | G8: =SUM(D8:F8) -> 383 | H8: =SUMIF('SAP DC Stock'!$L$5:$L$17,A8,'SAP DC Stock'!$E$5:$E$17)+SUMIF('Oracle Store Inv'!$L$5:$L$28,A8,'Oracle Store Inv'!$E$5:$E$28)+SUMIF('Oracle Store Inv'!$L$5:$L$28,A8,'Oracle Store Inv'!$F$5:$F$28)+SUMIF('3PL Warehouse Feed'!$K$5:$K$17,A8,'3PL Warehouse Feed'!$D$5:$D$17)+SUMIF('3PL Warehouse Feed'!$K$5:$K$17,A8,'3PL Warehouse Feed'!$E$5:$E$17) -> 0 | I8: =MAX(0,G8-H8) -> 383 | J8: =SUMIF('In-Transit'!$J$5:$J$12,A8,'In-Transit'!$K$5:$K$12) -> 34 | K8: =SUMIF('Open POs'!$L$5:$L$14,A8,'Open POs'!$M$5:$M$14) -> 131 | L8: =SUMIF('Sales History'!$G$5:$G$148,A8,'Sales History'!$H$5:$H$148) -> 937 | M8: =L8/12 -> 78.083333 | N8: =IF(M8=0,0,I8/M8) -> 4.905016 | O8: =VLOOKUP(A8,'Item Master'!$A$5:$K$16,6,FALSE) -> 735 | P8: =G8*O8 -> 281505 | Q8: =VLOOKUP(A8,'Item Master'!$A$5:$K$16,11,FALSE) -> Active | R8: =IF(A8="NX-1001","Possible duplicate SAP row",IF(A8="LT-3300","Missing Oracle cost on one row",IF(N8>6,"Excess cover",IF(N8<1,"Stockout risk","Review OK")))) -> Missing Oracle cost on one row
A9: AU-4100 | B9: Orbit ANC Headphones | C9: Audio | D9: =SUMIF('SAP DC Stock'!$L$5:$L$17,A9,'SAP DC Stock'!$N$5:$N$17) -> 183 | E9: =SUMIF('Oracle Store Inv'!$L$5:$L$28,A9,'Oracle Store Inv'!$N$5:$N$28) -> 54 | F9: =SUMIF('3PL Warehouse Feed'!$K$5:$K$17,A9,'3PL Warehouse Feed'!$M$5:$M$17) -> 176 | G9: =SUM(D9:F9) -> 413 | H9: =SUMIF('SAP DC Stock'!$L$5:$L$17,A9,'SAP DC Stock'!$E$5:$E$17)+SUMIF('Oracle Store Inv'!$L$5:$L$28,A9,'Oracle Store Inv'!$E$5:$E$28)+SUMIF('Oracle Store Inv'!$L$5:$L$28,A9,'Oracle Store Inv'!$F$5:$F$28)+SUMIF('3PL Warehouse Feed'!$K$5:$K$17,A9,'3PL Warehouse Feed'!$D$5:$D$17)+SUMIF('3PL Warehouse Feed'!$K$5:$K$17,A9,'3PL Warehouse Feed'!$E$5:$E$17) -> 12 | I9: =MAX(0,G9-H9) -> 401 | J9: =SUMIF('In-Transit'!$J$5:$J$12,A9,'In-Transit'!$K$5:$K$12) -> 43 | K9: =SUMIF('Open POs'!$L$5:$L$14,A9,'Open POs'!$M$5:$M$14) -> 148 | L9: =SUMIF('Sales History'!$G$5:$G$148,A9,'Sales History'!$H$5:$H$148) -> 1120 | M9: =L9/12 -> 93.333333 | N9: =IF(M9=0,0,I9/M9) -> 4.2964286 | O9: =VLOOKUP(A9,'Item Master'!$A$5:$K$16,6,FALSE) -> 86 | P9: =G9*O9 -> 35518 | Q9: =VLOOKUP(A9,'Item Master'!$A$5:$K$16,11,FALSE) -> Active | R9: =IF(A9="NX-1001","Possible duplicate SAP row",IF(A9="LT-3300","Missing Oracle cost on one row",IF(N9>6,"Excess cover",IF(N9<1,"Stockout risk","Review OK")))) -> Review OK
A10: AU-4200 | B10: Pulse Wireless Earbuds | C10: Audio | D10: =SUMIF('SAP DC Stock'!$L$5:$L$17,A10,'SAP DC Stock'!$N$5:$N$17) -> 220 | E10: =SUMIF('Oracle Store Inv'!$L$5:$L$28,A10,'Oracle Store Inv'!$N$5:$N$28) -> 76 | F10: =SUMIF('3PL Warehouse Feed'!$K$5:$K$17,A10,'3PL Warehouse Feed'!$M$5:$M$17) -> 205 | G10: =SUM(D10:F10) -> 501 | H10: =SUMIF('SAP DC Stock'!$L$5:$L$17,A10,'SAP DC Stock'!$E$5:$E$17)+SUMIF('Oracle Store Inv'!$L$5:$L$28,A10,'Oracle Store Inv'!$E$5:$E$28)+SUMIF('Oracle Store Inv'!$L$5:$L$28,A10,'Oracle Store Inv'!$F$5:$F$28)+SUMIF('3PL Warehouse Feed'!$K$5:$K$17,A10,'3PL Warehouse Feed'!$D$5:$D$17)+SUMIF('3PL Warehouse Feed'!$K$5:$K$17,A10,'3PL Warehouse Feed'!$E$5:$E$17) -> 13 | I10: =MAX(0,G10-H10) -> 488 | J10: =SUMIF('In-Transit'!$J$5:$J$12,A10,'In-Transit'!$K$5:$K$12) -> 52 | K10: =SUMIF('Open POs'!$L$5:$L$14,A10,'Open POs'!$M$5:$M$14) -> 165 | L10: =SUMIF('Sales History'!$G$5:$G$148,A10,'Sales History'!$H$5:$H$148) -> 1302 | M10: =L10/12 -> 108.5 | N10: =IF(M10=0,0,I10/M10) -> 4.4976959 | O10: =VLOOKUP(A10,'Item Master'!$A$5:$K$16,6,FALSE) -> 44 | P10: =G10*O10 -> 22044 | Q10: =VLOOKUP(A10,'Item Master'!$A$5:$K$16,11,FALSE) -> Active | R10: =IF(A10="NX-1001","Possible duplicate SAP row",IF(A10="LT-3300","Missing Oracle cost on one row",IF(N10>6,"Excess cover",IF(N10<1,"Stockout risk","Review OK")))) -> Review OK
A11: HM-5100 | B11: Halo Smart Speaker | C11: Smart Home | D11: =SUMIF('SAP DC Stock'!$L$5:$L$17,A11,'SAP DC Stock'!$N$5:$N$17) -> 257 | E11: =SUMIF('Oracle Store Inv'!$L$5:$L$28,A11,'Oracle Store Inv'!$N$5:$N$28) -> 40 | F11: =SUMIF('3PL Warehouse Feed'!$K$5:$K$17,A11,'3PL Warehouse Feed'!$M$5:$M$17) -> 234 | G11: =SUM(D11:F11) -> 531 | H11: =SUMIF('SAP DC Stock'!$L$5:$L$17,A11,'SAP DC Stock'!$E$5:$E$17)+SUMIF('Oracle Store Inv'!$L$5:$L$28,A11,'Oracle Store Inv'!$E$5:$E$28)+SUMIF('Oracle Store Inv'!$L$5:$L$28,A11,'Oracle Store Inv'!$F$5:$F$28)+SUMIF('3PL Warehouse Feed'!$K$5:$K$17,A11,'3PL Warehouse Feed'!$D$5:$D$17)+SUMIF('3PL Warehouse Feed'!$K$5:$K$17,A11,'3PL Warehouse Feed'!$E$5:$E$17) -> 5 | I11: =MAX(0,G11-H11) -> 526 | J11: =SUMIF('In-Transit'!$J$5:$J$12,A11,'In-Transit'!$K$5:$K$12) -> 61 | K11: =SUMIF('Open POs'!$L$5:$L$14,A11,'Open POs'!$M$5:$M$14) -> 182 | L11: =SUMIF('Sales History'!$G$5:$G$148,A11,'Sales History'!$H$5:$H$148) -> 1483 | M11: =L11/12 -> 123.58333 | N11: =IF(M11=0,0,I11/M11) -> 4.2562374 | O11: =VLOOKUP(A11,'Item Master'!$A$5:$K$16,6,FALSE) -> 57 | P11: =G11*O11 -> 30267 | Q11: =VLOOKUP(A11,'Item Master'!$A$5:$K$16,11,FALSE) -> Phase Out | R11: =IF(A11="NX-1001","Possible duplicate SAP row",IF(A11="LT-3300","Missing Oracle cost on one row",IF(N11>6,"Excess cover",IF(N11<1,"Stockout risk","Review OK")))) -> Review OK
A12: HM-5200 | B12: Sentinel Video Doorbell | C12: Smart Home | D12: =SUMIF('SAP DC Stock'!$L$5:$L$17,A12,'SAP DC Stock'!$N$5:$N$17) -> 294 | E12: =SUMIF('Oracle Store Inv'!$L$5:$L$28,A12,'Oracle Store Inv'!$N$5:$N$28) -> 62 | F12: =SUMIF('3PL Warehouse Feed'!$K$5:$K$17,A12,'3PL Warehouse Feed'!$M$5:$M$17) -> 263 | G12: =SUM(D12:F12) -> 619 | H12: =SUMIF('SAP DC Stock'!$L$5:$L$17,A12,'SAP DC Stock'!$E$5:$E$17)+SUMIF('Oracle Store Inv'!$L$5:$L$28,A12,'Oracle Store Inv'!$E$5:$E$28)+SUMIF('Oracle Store Inv'!$L$5:$L$28,A12,'Oracle Store Inv'!$F$5:$F$28)+SUMIF('3PL Warehouse Feed'!$K$5:$K$17,A12,'3PL Warehouse Feed'!$D$5:$D$17)+SUMIF('3PL Warehouse Feed'!$K$5:$K$17,A12,'3PL Warehouse Feed'!$E$5:$E$17) -> 2 | I12: =MAX(0,G12-H12) -> 617 | J12: =SUMIF('In-Transit'!$J$5:$J$12,A12,'In-Transit'!$K$5:$K$12) -> 70 | K12: =SUMIF('Open POs'!$L$5:$L$14,A12,'Open POs'!$M$5:$M$14) -> 199 | L12: =SUMIF('Sales History'!$G$5:$G$148,A12,'Sales History'!$H$5:$H$148) -> 1665 | M12: =L12/12 -> 138.75 | N12: =IF(M12=0,0,I12/M12) -> 4.4468468 | O12: =VLOOKUP(A12,'Item Master'!$A$5:$K$16,6,FALSE) -> 71 | P12: =G12*O12 -> 43949 | Q12: =VLOOKUP(A12,'Item Master'!$A$5:$K$16,11,FALSE) -> Active | R12: =IF(A12="NX-1001","Possible duplicate SAP row",IF(A12="LT-3300","Missing Oracle cost on one row",IF(N12>6,"Excess cover",IF(N12<1,"Stockout risk","Review OK")))) -> Review OK
A13: AC-6100 | B13: 65W USB-C Power Adapter | C13: Accessories | D13: =SUMIF('SAP DC Stock'!$L$5:$L$17,A13,'SAP DC Stock'!$N$5:$N$17) -> 3972 | E13: =SUMIF('Oracle Store Inv'!$L$5:$L$28,A13,'Oracle Store Inv'!$N$5:$N$28) -> 84 | F13: =SUMIF('3PL Warehouse Feed'!$K$5:$K$17,A13,'3PL Warehouse Feed'!$M$5:$M$17) -> 192 | G13: =SUM(D13:F13) -> 4248 | H13: =SUMIF('SAP DC Stock'!$L$5:$L$17,A13,'SAP DC Stock'!$E$5:$E$17)+SUMIF('Oracle Store Inv'!$L$5:$L$28,A13,'Oracle Store Inv'!$E$5:$E$28)+SUMIF('Oracle Store Inv'!$L$5:$L$28,A13,'Oracle Store Inv'!$F$5:$F$28)+SUMIF('3PL Warehouse Feed'!$K$5:$K$17,A13,'3PL Warehouse Feed'!$D$5:$D$17)+SUMIF('3PL Warehouse Feed'!$K$5:$K$17,A13,'3PL Warehouse Feed'!$E$5:$E$17) -> 12 | I13: =MAX(0,G13-H13) -> 4236 | J13: =SUMIF('In-Transit'!$J$5:$J$12,A13,'In-Transit'!$K$5:$K$12) -> 79 | K13: =SUMIF('Open POs'!$L$5:$L$14,A13,'Open POs'!$M$5:$M$14) -> 216 | L13: =SUMIF('Sales History'!$G$5:$G$148,A13,'Sales History'!$H$5:$H$148) -> 518 | M13: =L13/12 -> 43.166667 | N13: =IF(M13=0,0,I13/M13) -> 98.131274 | O13: =VLOOKUP(A13,'Item Master'!$A$5:$K$16,6,FALSE) -> 14 | P13: =G13*O13 -> 59472 | Q13: =VLOOKUP(A13,'Item Master'!$A$5:$K$16,11,FALSE) -> Active | R13: =IF(A13="NX-1001","Possible duplicate SAP row",IF(A13="LT-3300","Missing Oracle cost on one row",IF(N13>6,"Excess cover",IF(N13<1,"Stockout risk","Review OK")))) -> Excess cover
A14: AC-6200 | B14: Braided USB-C Cable 2m | C14: Accessories | D14: =SUMIF('SAP DC Stock'!$L$5:$L$17,A14,'SAP DC Stock'!$N$5:$N$17) -> 8832 | E14: =SUMIF('Oracle Store Inv'!$L$5:$L$28,A14,'Oracle Store Inv'!$N$5:$N$28) -> 106 | F14: =SUMIF('3PL Warehouse Feed'!$K$5:$K$17,A14,'3PL Warehouse Feed'!$M$5:$M$17) -> 408 | G14: =SUM(D14:F14) -> 9346 | H14: =SUMIF('SAP DC Stock'!$L$5:$L$17,A14,'SAP DC Stock'!$E$5:$E$17)+SUMIF('Oracle Store Inv'!$L$5:$L$28,A14,'Oracle Store Inv'!$E$5:$E$28)+SUMIF('Oracle Store Inv'!$L$5:$L$28,A14,'Oracle Store Inv'!$F$5:$F$28)+SUMIF('3PL Warehouse Feed'!$K$5:$K$17,A14,'3PL Warehouse Feed'!$D$5:$D$17)+SUMIF('3PL Warehouse Feed'!$K$5:$K$17,A14,'3PL Warehouse Feed'!$E$5:$E$17) -> 3 | I14: =MAX(0,G14-H14) -> 9343 | J14: =SUMIF('In-Transit'!$J$5:$J$12,A14,'In-Transit'!$K$5:$K$12) -> 88 | K14: =SUMIF('Open POs'!$L$5:$L$14,A14,'Open POs'!$M$5:$M$14) -> 456 | L14: =SUMIF('Sales History'!$G$5:$G$148,A14,'Sales History'!$H$5:$H$148) -> 700 | M14: =L14/12 -> 58.333333 | N14: =IF(M14=0,0,I14/M14) -> 160.16571 | O14: =VLOOKUP(A14,'Item Master'!$A$5:$K$16,6,FALSE) -> 4.2 | P14: =G14*O14 -> 39253.2 | Q14: =VLOOKUP(A14,'Item Master'!$A$5:$K$16,11,FALSE) -> End of Life | R14: =IF(A14="NX-1001","Possible duplicate SAP row",IF(A14="LT-3300","Missing Oracle cost on one row",IF(N14>6,"Excess cover",IF(N14<1,"Stockout risk","Review OK")))) -> Excess cover
A15: GM-7100 | B15: Vector Mechanical Keyboard | C15: Gaming | D15: =SUMIF('SAP DC Stock'!$L$5:$L$17,A15,'SAP DC Stock'!$N$5:$N$17) -> 405 | E15: =SUMIF('Oracle Store Inv'!$L$5:$L$28,A15,'Oracle Store Inv'!$N$5:$N$28) -> 70 | F15: =SUMIF('3PL Warehouse Feed'!$K$5:$K$17,A15,'3PL Warehouse Feed'!$M$5:$M$17) -> 110 | G15: =SUM(D15:F15) -> 585 | H15: =SUMIF('SAP DC Stock'!$L$5:$L$17,A15,'SAP DC Stock'!$E$5:$E$17)+SUMIF('Oracle Store Inv'!$L$5:$L$28,A15,'Oracle Store Inv'!$E$5:$E$28)+SUMIF('Oracle Store Inv'!$L$5:$L$28,A15,'Oracle Store Inv'!$F$5:$F$28)+SUMIF('3PL Warehouse Feed'!$K$5:$K$17,A15,'3PL Warehouse Feed'!$D$5:$D$17)+SUMIF('3PL Warehouse Feed'!$K$5:$K$17,A15,'3PL Warehouse Feed'!$E$5:$E$17) -> 18 | I15: =MAX(0,G15-H15) -> 567 | J15: =SUMIF('In-Transit'!$J$5:$J$12,A15,'In-Transit'!$K$5:$K$12) -> 0 | K15: =SUMIF('Open POs'!$L$5:$L$14,A15,'Open POs'!$M$5:$M$14) -> 0 | L15: =SUMIF('Sales History'!$G$5:$G$148,A15,'Sales History'!$H$5:$H$148) -> 884 | M15: =L15/12 -> 73.666667 | N15: =IF(M15=0,0,I15/M15) -> 7.6968326 | O15: =VLOOKUP(A15,'Item Master'!$A$5:$K$16,6,FALSE) -> 63 | P15: =G15*O15 -> 36855 | Q15: =VLOOKUP(A15,'Item Master'!$A$5:$K$16,11,FALSE) -> Active | R15: =IF(A15="NX-1001","Possible duplicate SAP row",IF(A15="LT-3300","Missing Oracle cost on one row",IF(N15>6,"Excess cover",IF(N15<1,"Stockout risk","Review OK")))) -> Excess cover
A16: GM-7200 | B16: Photon Gaming Mouse | C16: Gaming | D16: =SUMIF('SAP DC Stock'!$L$5:$L$17,A16,'SAP DC Stock'!$N$5:$N$17) -> 442 | E16: =SUMIF('Oracle Store Inv'!$L$5:$L$28,A16,'Oracle Store Inv'!$N$5:$N$28) -> 34 | F16: =SUMIF('3PL Warehouse Feed'!$K$5:$K$17,A16,'3PL Warehouse Feed'!$M$5:$M$17) -> 139 | G16: =SUM(D16:F16) -> 615 | H16: =SUMIF('SAP DC Stock'!$L$5:$L$17,A16,'SAP DC Stock'!$E$5:$E$17)+SUMIF('Oracle Store Inv'!$L$5:$L$28,A16,'Oracle Store Inv'!$E$5:$E$28)+SUMIF('Oracle Store Inv'!$L$5:$L$28,A16,'Oracle Store Inv'!$F$5:$F$28)+SUMIF('3PL Warehouse Feed'!$K$5:$K$17,A16,'3PL Warehouse Feed'!$D$5:$D$17)+SUMIF('3PL Warehouse Feed'!$K$5:$K$17,A16,'3PL Warehouse Feed'!$E$5:$E$17) -> 0 | I16: =MAX(0,G16-H16) -> 615 | J16: =SUMIF('In-Transit'!$J$5:$J$12,A16,'In-Transit'!$K$5:$K$12) -> 0 | K16: =SUMIF('Open POs'!$L$5:$L$14,A16,'Open POs'!$M$5:$M$14) -> 0 | L16: =SUMIF('Sales History'!$G$5:$G$148,A16,'Sales History'!$H$5:$H$148) -> 977 | M16: =L16/12 -> 81.416667 | N16: =IF(M16=0,0,I16/M16) -> 7.5537359 | O16: =VLOOKUP(A16,'Item Master'!$A$5:$K$16,6,FALSE) -> 31 | P16: =G16*O16 -> 19065 | Q16: =VLOOKUP(A16,'Item Master'!$A$5:$K$16,11,FALSE) -> Active | R16: =IF(A16="NX-1001","Possible duplicate SAP row",IF(A16="LT-3300","Missing Oracle cost on one row",IF(N16>6,"Excess cover",IF(N16<1,"Stockout risk","Review OK")))) -> Excess cover

Sheet Reserve Analysis
A1: Inventory Obsolescence Reserve
A2: Finance policy: reserve rate depends on lifecycle and months of supply. Calculations reference the consolidated position.
A4: SKU | B4: Product | C4: Gross Value USD | D4: Months Cover | E4: Lifecycle | F4: Base Reserve % | G4: Lifecycle Add-on % | H4: Total Reserve % | I4: Reserve USD | J4: Net Inventory USD
A5: =Consolidated!A5 -> NX-1001 | B5: =Consolidated!B5 -> Nova X1 Smartphone 128GB | C5: =Consolidated!P5 -> 102531 | D5: =Consolidated!N5 -> 6.989011 | E5: =Consolidated!Q5 -> Active | F5: =IF(D5>12,75%,IF(D5>9,50%,IF(D5>6,25%,IF(D5>3,10%,2%)))) -> 0.25 | G5: =IF(E5="End of Life",20%,IF(E5="Phase Out",10%,0%)) -> 0 | H5: =MIN(100%,F5+G5) -> 0.25 | I5: =C5*H5 -> 25632.75 | J5: =C5-I5 -> 76898.25
A6: =Consolidated!A6 -> NX-1002 | B6: =Consolidated!B6 -> Nova X1 Smartphone 256GB | C6: =Consolidated!P6 -> 101223 | D6: =Consolidated!N6 -> 4.3275261 | E6: =Consolidated!Q6 -> Active | F6: =IF(D6>12,75%,IF(D6>9,50%,IF(D6>6,25%,IF(D6>3,10%,2%)))) -> 0.1 | G6: =IF(E6="End of Life",20%,IF(E6="Phase Out",10%,0%)) -> 0 | H6: =MIN(100%,F6+G6) -> 0.1 | I6: =C6*H6 -> 10122.3 | J6: =C6-I6 -> 91100.7
A7: =Consolidated!A7 -> TB-2100 | B7: =Consolidated!B7 -> Atlas 11-inch Tablet | C7: =Consolidated!P7 -> 91450 | D7: =Consolidated!N7 -> 4.6507937 | E7: =Consolidated!Q7 -> Active | F7: =IF(D7>12,75%,IF(D7>9,50%,IF(D7>6,25%,IF(D7>3,10%,2%)))) -> 0.1 | G7: =IF(E7="End of Life",20%,IF(E7="Phase Out",10%,0%)) -> 0 | H7: =MIN(100%,F7+G7) -> 0.1 | I7: =C7*H7 -> 9145 | J7: =C7-I7 -> 82305
A8: =Consolidated!A8 -> LT-3300 | B8: =Consolidated!B8 -> Pioneer 14 Pro Laptop | C8: =Consolidated!P8 -> 281505 | D8: =Consolidated!N8 -> 4.905016 | E8: =Consolidated!Q8 -> Active | F8: =IF(D8>12,75%,IF(D8>9,50%,IF(D8>6,25%,IF(D8>3,10%,2%)))) -> 0.1 | G8: =IF(E8="End of Life",20%,IF(E8="Phase Out",10%,0%)) -> 0 | H8: =MIN(100%,F8+G8) -> 0.1 | I8: =C8*H8 -> 28150.5 | J8: =C8-I8 -> 253354.5
A9: =Consolidated!A9 -> AU-4100 | B9: =Consolidated!B9 -> Orbit ANC Headphones | C9: =Consolidated!P9 -> 35518 | D9: =Consolidated!N9 -> 4.2964286 | E9: =Consolidated!Q9 -> Active | F9: =IF(D9>12,75%,IF(D9>9,50%,IF(D9>6,25%,IF(D9>3,10%,2%)))) -> 0.1 | G9: =IF(E9="End of Life",20%,IF(E9="Phase Out",10%,0%)) -> 0 | H9: =MIN(100%,F9+G9) -> 0.1 | I9: =C9*H9 -> 3551.8 | J9: =C9-I9 -> 31966.2
A10: =Consolidated!A10 -> AU-4200 | B10: =Consolidated!B10 -> Pulse Wireless Earbuds | C10: =Consolidated!P10 -> 22044 | D10: =Consolidated!N10 -> 4.4976959 | E10: =Consolidated!Q10 -> Active | F10: =IF(D10>12,75%,IF(D10>9,50%,IF(D10>6,25%,IF(D10>3,10%,2%)))) -> 0.1 | G10: =IF(E10="End of Life",20%,IF(E10="Phase Out",10%,0%)) -> 0 | H10: =MIN(100%,F10+G10) -> 0.1 | I10: =C10*H10 -> 2204.4 | J10: =C10-I10 -> 19839.6
A11: =Consolidated!A11 -> HM-5100 | B11: =Consolidated!B11 -> Halo Smart Speaker | C11: =Consolidated!P11 -> 30267 | D11: =Consolidated!N11 -> 4.2562374 | E11: =Consolidated!Q11 -> Phase Out | F11: =IF(D11>12,75%,IF(D11>9,50%,IF(D11>6,25%,IF(D11>3,10%,2%)))) -> 0.1 | G11: =IF(E11="End of Life",20%,IF(E11="Phase Out",10%,0%)) -> 0.1 | H11: =MIN(100%,F11+G11) -> 0.2 | I11: =C11*H11 -> 6053.4 | J11: =C11-I11 -> 24213.6
A12: =Consolidated!A12 -> HM-5200 | B12: =Consolidated!B12 -> Sentinel Video Doorbell | C12: =Consolidated!P12 -> 43949 | D12: =Consolidated!N12 -> 4.4468468 | E12: =Consolidated!Q12 -> Active | F12: =IF(D12>12,75%,IF(D12>9,50%,IF(D12>6,25%,IF(D12>3,10%,2%)))) -> 0.1 | G12: =IF(E12="End of Life",20%,IF(E12="Phase Out",10%,0%)) -> 0 | H12: =MIN(100%,F12+G12) -> 0.1 | I12: =C12*H12 -> 4394.9 | J12: =C12-I12 -> 39554.1
A13: =Consolidated!A13 -> AC-6100 | B13: =Consolidated!B13 -> 65W USB-C Power Adapter | C13: =Consolidated!P13 -> 59472 | D13: =Consolidated!N13 -> 98.131274 | E13: =Consolidated!Q13 -> Active | F13: =IF(D13>12,75%,IF(D13>9,50%,IF(D13>6,25%,IF(D13>3,10%,2%)))) -> 0.75 | G13: =IF(E13="End of Life",20%,IF(E13="Phase Out",10%,0%)) -> 0 | H13: =MIN(100%,F13+G13) -> 0.75 | I13: =C13*H13 -> 44604 | J13: =C13-I13 -> 14868
A14: =Consolidated!A14 -> AC-6200 | B14: =Consolidated!B14 -> Braided USB-C Cable 2m | C14: =Consolidated!P14 -> 39253.2 | D14: =Consolidated!N14 -> 160.16571 | E14: =Consolidated!Q14 -> End of Life | F14: =IF(D14>12,75%,IF(D14>9,50%,IF(D14>6,25%,IF(D14>3,10%,2%)))) -> 0.75 | G14: =IF(E14="End of Life",20%,IF(E14="Phase Out",10%,0%)) -> 0.2 | H14: =MIN(100%,F14+G14) -> 0.95 | I14: =C14*H14 -> 37290.54 | J14: =C14-I14 -> 1962.66
A15: =Consolidated!A15 -> GM-7100 | B15: =Consolidated!B15 -> Vector Mechanical Keyboard | C15: =Consolidated!P15 -> 36855 | D15: =Consolidated!N15 -> 7.6968326 | E15: =Consolidated!Q15 -> Active | F15: =IF(D15>12,75%,IF(D15>9,50%,IF(D15>6,25%,IF(D15>3,10%,2%)))) -> 0.25 | G15: =IF(E15="End of Life",20%,IF(E15="Phase Out",10%,0%)) -> 0 | H15: =MIN(100%,F15+G15) -> 0.25 | I15: =C15*H15 -> 9213.75 | J15: =C15-I15 -> 27641.25
A16: =Consolidated!A16 -> GM-7200 | B16: =Consolidated!B16 -> Photon Gaming Mouse | C16: =Consolidated!P16 -> 19065 | D16: =Consolidated!N16 -> 7.5537359 | E16: =Consolidated!Q16 -> Active | F16: =IF(D16>12,75%,IF(D16>9,50%,IF(D16>6,25%,IF(D16>3,10%,2%)))) -> 0.25 | G16: =IF(E16="End of Life",20%,IF(E16="Phase Out",10%,0%)) -> 0 | H16: =MIN(100%,F16+G16) -> 0.25 | I16: =C16*H16 -> 4766.25 | J16: =C16-I16 -> 14298.75
A18: TOTAL | C18: =SUM(C5:C16) -> 863132.2 | I18: =SUM(I5:I16) -> 185129.59 | J18: =SUM(J5:J16) -> 678002.61

Sheet Checks
A1: Reconciliation & Data Quality Checks
A2: PASS means the calculation is internally consistent; WARN identifies intentional training exceptions requiring investigation.
A4: Check | B4: Actual | C4: Expected | D4: Difference | E4: Tolerance | F4: Status | G4: Where to Fix / Interpretation
A5: Consolidated gross units tie to source helper totals | B5: =SUM(Consolidated!G5:G16) -> 17982 | C5: =SUM('SAP DC Stock'!N5:N17)+SUM('Oracle Store Inv'!N5:N28)+SUM('3PL Warehouse Feed'!M5:M16) -> 17982 | D5: =B5-C5 -> 0 | E5: =0 -> 0 | F5: =IF(ABS(D5)<=E5,"PASS","FAIL") -> PASS | G5: Consolidated; excludes intentionally unmapped 3PL row
A6: Unmapped 3PL SKU quantity | B6: =SUMIF('3PL Warehouse Feed'!K5:K17,"UNMAPPED",'3PL Warehouse Feed'!M5:M17) -> 25 | C6: =0 -> 0 | D6: =B6-C6 -> 25 | E6: =0 -> 0 | F6: =IF(D6=0,"PASS","WARN") -> WARN | G6: 3PL Warehouse Feed row 17 / Item Master
A7: Missing Oracle unit cost rows | B7: =COUNTBLANK('Oracle Store Inv'!H5:H28) -> 1 | C7: =0 -> 0 | D7: =B7-C7 -> 1 | E7: =0 -> 0 | F7: =IF(D7=0,"PASS","WARN") -> WARN | G7: Oracle Store Inv Retail Cost
A8: Stale Oracle count rows before close date | B8: =COUNTIF('Oracle Store Inv'!J5:J28,"<"&DATE(2026,7,31)) -> 3 | C8: =0 -> 0 | D8: =B8-C8 -> 3 | E8: =0 -> 0 | F8: =IF(D8=0,"PASS","WARN") -> WARN | G8: Oracle Store Inv Stocktake Date
A9: SAP repeated material/location indicator | B9: =COUNTIFS('SAP DC Stock'!A5:A17,"NX-1001",'SAP DC Stock'!B5:B17,"US01") -> 2 | C9: =1 -> 1 | D9: =B9-C9 -> 1 | E9: =0 -> 0 | F9: =IF(D9<=0,"PASS","WARN") -> WARN | G9: SAP DC Stock — verify batch/detail granularity
A10: Reserve roll-forward arithmetic | B10: ='Reserve Analysis'!C18-'Reserve Analysis'!I18-'Reserve Analysis'!J18 -> 0 | C10: =0 -> 0 | D10: =B10-C10 -> 0 | E10: =0.01 -> 0.01 | F10: =IF(ABS(D10)<=E10,"PASS","FAIL") -> PASS | G10: Reserve Analysis totals
A11: Open PO base units positive | B11: =MIN('Open POs'!M5:M14) -> 80 | C11: =1 -> 1 | D11: =B11-C11 -> 79 | E11: =0 -> 0 | F11: =IF(B11>=C11,"PASS","FAIL") -> PASS | G11: Open POs quantity/UOM
A12: Sales history contains return activity | B12: =COUNTIF('Sales History'!E5:E148,"<0") -> 24 | C12: =1 -> 1 | D12: =B12-C12 -> 23 | E12: =0 -> 0 | F12: =IF(B12>=C12,"PASS","WARN") -> PASS | G12: Valid negative returns; do not reject automatically
A15: MODEL STATUS | C15: =IF(COUNTIF(F5:F12,"FAIL")=0,"PASS WITH WARNINGS","FAIL") -> PASS WITH WARNINGS

Sheet Source Log
A1: Source & Refresh Log
A2: Synthetic source documentation for auditability. URLs intentionally identify example system categories rather than real company data.
A4: Source ID | B4: Source System | C4: Report / Extract | D4: As-of | E4: Refresh Frequency | F4: Owner | G4: Primary Keys | H4: Known Limitations | I4: Reference
A5: SRC-01 | B5: SAP S/4HANA | C5: MB52 Inventory by Plant/SLoc | D5: 46234 | E5: Daily | F5: Supply Chain Finance | G5: Material + Plant + SLoc + Batch | H5: Repeated material/location lines may be legitimate batches | I5: https://www.sap.com/products/erp/s4hana.html
A6: SRC-02 | B6: Oracle Retail | C6: Store Inventory Snapshot | D6: 46234 | E6: Daily | F6: Retail Accounting | G6: Org + Item | H6: Some stores close late; costs can be blank during item setup | I6: https://www.oracle.com/industries/retail/
A7: SRC-03 | B7: NorthStar 3PL WMS | C7: Client Inventory Feed | D7: 46234 | E7: Hourly | F7: Logistics Operations | G7: Facility + Client Item + Status | H7: Partner aliases and text timestamps require mapping | I7: Synthetic partner feed
A8: SRC-04 | B8: Procurement Tracker | C8: Open PO Schedule | D8: 46234 | E8: Weekly | F8: Procurement Finance | G8: PO + Line | H8: Expected dates change; status is manually maintained | I8: Synthetic procurement extract
A9: SRC-05 | B9: Treasury | C9: Month-end FX rates | D9: 46234 | E9: Monthly | F9: Treasury | G9: Currency + Rate Date | H9: Rates are fictional for training | I9: Synthetic close-rate table
