Workbook

Sheet Read Me First
A1: BUCEPHALUS STRESS-TEST WORKBOOK
A2: A difficult but resolvable demo for workbook discovery, normalization, validation, forecasting, and Botpress context sharing.
A4: How to test
A5: 1 | B5: Open the Bucephalus task pane and select Enterprise Workbook.
A6: 2 | B6: Rescan the workbook and review every detected dataset and mapping.
A7: 3 | B7: Resolve blockers: map/exclude the unknown and ambiguous SKUs, and exclude the CHF purchase-order row or add an FX rate.
A8: 4 | B8: For duplicate review, exclude the exact repeat but keep the two different batch rows as distinct.
A9: 5 | B9: Confirm warnings, run Enterprise Analysis, and then share the compact context with Ask Bucephalus.
A11: Intentional review cases
A12: Blocker | B12: ZZ-UNKNOWN-01 | C12: Unknown SKU in Oracle Retail Count; map or exclude the row.
A13: Blocker | B13: SHARED-DEMO | C13: Alias belongs to two audio SKUs; select the intended SKU or exclude.
A14: Blocker | B14: CHF PO | C14: One procurement row uses CHF without an FX rate; add CHF to Reference Tables or exclude the row.
A15: Duplicate | B15: Exact repeat | C15: SAP row for EL-1001/DC-NJ is repeated exactly; choose Exclude repeats.
A16: Duplicate | B16: Different batches | C16: Two EL-2001/DC-TX rows have different batch IDs and quantities; keep them distinct.
A17: Warning | B17: Missing cost | C17: One 3PL row has no source cost; the item-master standard cost should be used.
A18: Warning | B18: Stale dates | C18: Several retail records are older than the newest inventory snapshot.
A19: Edge case | B19: Negative returns | C19: One historical returns value is negative and should remain valid.
A20: Edge case | B20: Mixed UOM | C20: EA, CS, and PACK quantities use SKU-specific conversion factors.
A21: Supply | B21: Customs/Delayed | C21: Held or delayed transfers should be visible but not treated as immediately available.

Sheet Global Product Register
A1: Global Product Register
A2: Authoritative item master. Aliases are intentionally varied; SHARED-DEMO is ambiguous by design.
A4: Master SKU | B4: Material Description | C4: Merchandise Group | D4: Known Source Aliases | E4: Base UoM | F4: Case Pack | G4: Standard Unit Cost | H4: Local Currency | I4: Lifecycle
A5: EL-1001 | B5: Nova X1 Smartphone 128GB | C5: Mobile | D5: N-X1-128 | NX1001 | E5: EA | F5: 10 | G5: 310 | H5: USD | I5: Active
A6: EL-1002 | B6: Nova X1 Smartphone 256GB | C6: Mobile | D6: N-X1-256 | NX1002 | E6: EA | F6: 8 | G6: 420 | H6: USD | I6: Active
A7: EL-2001 | B7: Atlas 14 Pro Laptop | C7: Computing | D7: A14-LT | LT-AT14 | E7: EA | F7: 4 | G7: 735 | H7: USD | I7: Active
A8: EL-2002 | B8: Atlas 11-inch Tablet | C8: Computing | D8: AT-11 | TB1100 | E8: EA | F8: 6 | G8: 310 | H8: USD | I8: Active
A9: AU-3001 | B9: Orbit ANC Headphones | C9: Audio | D9: ORB-ANC | HEAD-ORB | SHARED-DEMO | E9: EA | F9: 12 | G9: 86 | H9: USD | I9: Active
A10: AU-3002 | B10: Pulse Wireless Earbuds | C10: Audio | D10: PULSE-BUD | BUD3002 | SHARED-DEMO | E10: EA | F10: 24 | G10: 44 | H10: USD | I10: Active
A11: GM-4001 | B11: Vector Mechanical Keyboard | C11: Gaming | D11: VEC-KB | VK4001 | E11: EA | F11: 10 | G11: 63 | H11: USD | I11: Active
A12: GM-4002 | B12: Photon Gaming Mouse | C12: Gaming | D12: PH-MOUSE | PGM4002 | E12: EA | F12: 20 | G12: 31 | H12: USD | I12: Active
A13: HM-5001 | B13: Halo Smart Speaker | C13: Smart Home | D13: HALO-SPK | HS5001 | E13: EA | F13: 8 | G13: 57 | H13: USD | I13: Active
A14: HM-5002 | B14: Sentinel Video Doorbell | C14: Smart Home | D14: SENT-DB | SV5002 | E14: EA | F14: 6 | G14: 71 | H14: USD | I14: Active
A15: AC-6001 | B15: 65W USB-C Power Adapter | C15: Accessories | D15: PWR65 | PA6001 | E15: EA | F15: 30 | G15: 14 | H15: EUR | I15: Active
A16: AC-6002 | B16: Braided USB-C Cable 2m | C16: Accessories | D16: CBL-2M | CB6002 | E16: EA | F16: 50 | G16: 4.2 | H16: EUR | I16: Active
... A18: OF-7002 | B18: HD Conference Camera | C18: Office | D18: CONF-CAM | HC7002 | E18: EA | F18: 8 | G18: 16500 | H18: JPY | I18: Phase Out

Sheet SAP Distribution Stock
A1: SAP Distribution Stock
A2: ERP snapshot with mixed EA/CS quantities, restrictions, an exact repeat, and a legitimate alternate batch.
A5: Material | B5: Plant | C5: Stock Type | D5: Unrestricted Qty | E5: Customer Reserve | F5: QI | G5: Damaged Qty | H5: Qty UOM | I5: MAP | J5: Company Code Currency | K5: Snapshot Date | L5: Batch
A6: N-X1-128 | B6: DC-NJ | C6: Unrestricted | D6: 4 | E6: 8 | F6: 3 | G6: 2 | H6: CS | I6: 310 | J6: USD | K6: 46235 | L6: B-1-1
A7: N-X1-128 | B7: DC-TX | C7: Unrestricted | D7: 84 | E7: 0 | F7: 0 | G7: 0 | H7: EA | I7: 310 | J7: USD | K7: 46235 | L7: B-1-2
A8: EL-1002 | B8: DC-NJ | C8: Unrestricted | D8: 102 | E8: 0 | F8: 0 | G8: 0 | H8: EA | I8: 420 | J8: USD | K8: 46235 | L8: B-2-1
A9: EL-1002 | B9: DC-TX | C9: Unrestricted | D9: 121 | E9: 0 | F9: 0 | G9: 0 | H9: EA | I9: 420 | J9: USD | K9: 46235 | L9: B-2-2
A10: EL-2001 | B10: DC-NJ | C10: Unrestricted | D10: 139 | E10: 0 | F10: 0 | G10: 0 | H10: EA | I10: 735 | J10: USD | K10: 46235 | L10: B-3-1
A11: EL-2001 | B11: DC-TX | C11: Unrestricted | D11: 158 | E11: 0 | F11: 0 | G11: 0 | H11: EA | I11: 735 | J11: USD | K11: 46235 | L11: B-3-2
A12: EL-2002 | B12: DC-NJ | C12: Unrestricted | D12: 176 | E12: 0 | F12: 0 | G12: 0 | H12: EA | I12: 310 | J12: USD | K12: 46235 | L12: B-4-1
A13: EL-2002 | B13: DC-TX | C13: Unrestricted | D13: 7 | E13: 0 | F13: 0 | G13: 0 | H13: CS | I13: 310 | J13: USD | K13: 46235 | L13: B-4-2
A14: AU-3001 | B14: DC-NJ | C14: Unrestricted | D14: 8 | E14: 0 | F14: 0 | G14: 0 | H14: CS | I14: 86 | J14: USD | K14: 46235 | L14: B-5-1
A15: AU-3001 | B15: DC-TX | C15: Unrestricted | D15: 232 | E15: 0 | F15: 0 | G15: 0 | H15: EA | I15: 86 | J15: USD | K15: 46235 | L15: B-5-2
A16: PULSE-BUD | B16: DC-NJ | C16: Unrestricted | D16: 250 | E16: 0 | F16: 0 | G16: 0 | H16: EA | I16: 44 | J16: USD | K16: 46235 | L16: B-6-1
A17: PULSE-BUD | B17: DC-TX | C17: Unrestricted | D17: 269 | E17: 8 | F17: 0 | G17: 0 | H17: EA | I17: 44 | J17: USD | K17: 46235 | L17: B-6-2
... A35: EL-2001 | B35: DC-TX | C35: Unrestricted | D35: 37 | E35: 0 | F35: 0 | G35: 0 | H35: EA | I35: 735 | J35: USD | K35: 46235 | L35: B-LAPTOP-ALT

Sheet Oracle Retail Count
A1: Oracle Retail Count
A2: Retail stores use different aliases and headers. Includes stale rows, a missing cost, an unknown SKU, and an ambiguous alias.
A6: Product Code | B6: Store | C6: SOH | D6: Allocated | E6: Hold Qty | F6: Selling UOM | G6: Retail Cost | H6: Curr | I6: As Of
A7: N-X1-128 | B7: NYC-01 | C7: 28 | D7: 5 | E7: 2 | F7: EA | G7: 310 | H7: USD | I7: 46227
A8: N-X1-128 | B8: CHI-02 | C8: 39 | D8: 0 | E8: 0 | F8: EA | G8: 310 | H8: USD | I8: 46235
A9: EL-1002 | B9: NYC-01 | C9: 57 | D9: 0 | E9: 0 | F9: EA | G9: 420 | H9: USD | I9: 46227
A10: EL-1002 | B10: CHI-02 | C10: 68 | D10: 0 | E10: 0 | F10: EA | G10: 420 | H10: USD | I10: 46235
A11: EL-2001 | B11: NYC-01 | C11: 86 | D11: 0 | E11: 0 | F11: EA | G11: 735 | H11: USD | I11: 46227
A12: EL-2001 | B12: CHI-02 | C12: 97 | D12: 0 | E12: 0 | F12: EA | G12: 735 | H12: USD | I12: 46235
A13: AT-11 | B13: NYC-01 | C13: 115 | D13: 0 | E13: 0 | F13: EA | G13: 310 | H13: USD | I13: 46235
A14: AT-11 | B14: CHI-02 | C14: 126 | D14: 0 | E14: 0 | F14: EA | G14: 310 | H14: USD | I14: 46235
A15: AU-3001 | B15: NYC-01 | C15: 144 | D15: 0 | E15: 0 | F15: EA | G15: 86 | H15: USD | I15: 46235
A16: AU-3001 | B16: CHI-02 | C16: 35 | D16: 0 | E16: 0 | F16: EA | G16: 86 | H16: USD | I16: 46235
A17: AU-3002 | B17: NYC-01 | C17: 53 | D17: 0 | E17: 0 | F17: EA | G17: 44 | H17: USD | I17: 46235
A18: AU-3002 | B18: CHI-02 | C18: 64 | D18: 0 | E18: 0 | F18: EA | G18: 44 | H18: USD | I18: 46235
... A21: GM-4002 | B21: NYC-01 | C21: 111 | D21: 5 | E21: 0 | F21: EA | G21: 31 | H21: USD | I21: 46235
A22: GM-4002 | B22: CHI-02 | C22: 122 | D22: 0 | E22: 0 | F22: EA | H22: USD | I22: 46235
A23: HM-5001 | B23: NYC-01 | C23: 140 | D23: 0 | E23: 0 | F23: EA | G23: 57 | H23: USD | I23: 46235
A24: HM-5001 | B24: CHI-02 | C24: 31 | D24: 0 | E24: 0 | F24: EA | G24: 57 | H24: USD | I24: 46235
A25: SENT-DB | B25: NYC-01 | C25: 49 | D25: 0 | E25: 0 | F25: EA | G25: 71 | H25: USD | I25: 46235
A26: SENT-DB | B26: CHI-02 | C26: 60 | D26: 0 | E26: 2 | F26: EA | G26: 71 | H26: USD | I26: 46235
A27: AC-6001 | B27: NYC-01 | C27: 78 | D27: 0 | E27: 2 | F27: EA | G27: 14 | H27: EUR | I27: 46235
A28: AC-6001 | B28: CHI-02 | C28: 89 | D28: 0 | E28: 0 | F28: EA | G28: 14 | H28: EUR | I28: 46235
A29: AC-6002 | B29: NYC-01 | C29: 107 | D29: 0 | E29: 0 | F29: EA | G29: 4.2 | H29: EUR | I29: 46235
A30: AC-6002 | B30: CHI-02 | C30: 118 | D30: 0 | E30: 0 | F30: EA | G30: 4.2 | H30: EUR | I30: 46235
A31: ERGO-SET | B31: NYC-01 | C31: 136 | D31: 0 | E31: 0 | F31: EA | G31: 95 | H31: CAD | I31: 46235
A32: ERGO-SET | B32: CHI-02 | C32: 147 | D32: 0 | E32: 0 | F32: EA | G32: 95 | H32: CAD | I32: 46235
A33: OF-7002 | B33: NYC-01 | C33: 45 | D33: 0 | E33: 0 | F33: EA | G33: 16500 | H33: JPY | I33: 46235
A34: OF-7002 | B34: CHI-02 | C34: 56 | D34: 5 | E34: 0 | F34: EA | G34: 16500 | H34: JPY | I34: 46235
... A36: SHARED-DEMO | B36: CHI-02 | C36: 12 | D36: 0 | E36: 0 | F36: EA | G36: 50 | H36: USD | I36: 46235

Sheet 3PL External Feed
A1: External Logistics Feed
A2: Case and pack quantities require item-specific conversions; one cost is intentionally missing.
A4: Client Item | B4: Facility | C4: Inventory Status | D4: Stock | E4: Reserved | F4: Quality Hold | G4: Damage Qty | H4: Order UOM | I4: Declared Cost | J4: Currency Code | K4: Stocktake Date | L4: Lot Number
A5: NX1001 | B5: 3PL-EAST | C5: Available | D5: 2 | E5: 1 | F5: 1 | G5: 0 | H5: PACK | I5: 310 | J5: USD | K5: 46235 | L5: 3PL-01-1
A6: NX1001 | B6: 3PL-WEST | C6: Available | D6: 3 | E6: 0 | F6: 0 | G6: 0 | H6: CS | I6: 310 | J6: USD | K6: 46235 | L6: 3PL-01-2
A7: NX1002 | B7: 3PL-EAST | C7: Available | D7: 3 | E7: 0 | F7: 0 | G7: 0 | H7: CS | I7: 420 | J7: USD | K7: 46235 | L7: 3PL-02-1
A8: NX1002 | B8: 3PL-WEST | C8: Available | D8: 4 | E8: 0 | F8: 0 | G8: 0 | H8: PACK | I8: 420 | J8: USD | K8: 46235 | L8: 3PL-02-2
A9: LT-AT14 | B9: 3PL-EAST | C9: Available | D9: 4 | E9: 0 | F9: 0 | G9: 0 | H9: PACK | I9: 735 | J9: USD | K9: 46235 | L9: 3PL-03-1
A10: LT-AT14 | B10: 3PL-WEST | C10: Available | D10: 5 | E10: 0 | F10: 0 | G10: 0 | H10: CS | I10: 735 | J10: USD | K10: 46235 | L10: 3PL-03-2
A11: TB1100 | B11: 3PL-EAST | C11: Available | D11: 5 | E11: 0 | F11: 0 | G11: 0 | H11: CS | I11: 310 | J11: USD | K11: 46235 | L11: 3PL-04-1
A12: TB1100 | B12: 3PL-WEST | C12: Available | D12: 6 | E12: 0 | F12: 0 | G12: 0 | H12: PACK | I12: 310 | J12: USD | K12: 46235 | L12: 3PL-04-2
A13: HEAD-ORB | B13: 3PL-EAST | C13: Available | D13: 6 | E13: 0 | F13: 0 | G13: 0 | H13: PACK | J13: USD | K13: 46235 | L13: 3PL-05-1
A14: HEAD-ORB | B14: 3PL-WEST | C14: Available | D14: 7 | E14: 0 | F14: 0 | G14: 0 | H14: CS | I14: 86 | J14: USD | K14: 46235 | L14: 3PL-05-2
A15: BUD3002 | B15: 3PL-EAST | C15: Available | D15: 7 | E15: 0 | F15: 0 | G15: 0 | H15: CS | I15: 44 | J15: USD | K15: 46235 | L15: 3PL-06-1
A16: BUD3002 | B16: 3PL-WEST | C16: Available | D16: 8 | E16: 0 | F16: 0 | G16: 0 | H16: PACK | I16: 44 | J16: USD | K16: 46235 | L16: 3PL-06-2
A17: VK4001 | B17: 3PL-EAST | C17: Available | D17: 8 | E17: 0 | F17: 0 | G17: 0 | H17: PACK | I17: 63 | J17: USD | K17: 46235 | L17: 3PL-07-1
A18: VK4001 | B18: 3PL-WEST | C18: Available | D18: 9 | E18: 0 | F18: 0 | G18: 0 | H18: CS | I18: 63 | J18: USD | K18: 46235 | L18: 3PL-07-2
A19: PGM4002 | B19: 3PL-EAST | C19: Available | D19: 9 | E19: 0 | F19: 0 | G19: 0 | H19: CS | I19: 31 | J19: USD | K19: 46235 | L19: 3PL-08-1
A20: PGM4002 | B20: 3PL-WEST | C20: Available | D20: 2 | E20: 1 | F20: 0 | G20: 0 | H20: PACK | I20: 31 | J20: USD | K20: 46235 | L20: 3PL-08-2
A21: HS5001 | B21: 3PL-EAST | C21: Available | D21: 2 | E21: 1 | F21: 0 | G21: 0 | H21: PACK | I21: 57 | J21: USD | K21: 46235 | L21: 3PL-09-1
A22: HS5001 | B22: 3PL-WEST | C22: Available | D22: 3 | E22: 0 | F22: 1 | G22: 0 | H22: CS | I22: 57 | J22: USD | K22: 46235 | L22: 3PL-09-2
A23: SV5002 | B23: 3PL-EAST | C23: Available | D23: 3 | E23: 0 | F23: 1 | G23: 0 | H23: CS | I23: 71 | J23: USD | K23: 46235 | L23: 3PL-10-1
A24: SV5002 | B24: 3PL-WEST | C24: Available | D24: 4 | E24: 0 | F24: 0 | G24: 0 | H24: PACK | I24: 71 | J24: USD | K24: 46235 | L24: 3PL-10-2
A25: PA6001 | B25: 3PL-EAST | C25: Available | D25: 4 | E25: 0 | F25: 0 | G25: 0 | H25: PACK | I25: 14 | J25: EUR | K25: 46235 | L25: 3PL-11-1
... A32: HC7002 | B32: 3PL-WEST | C32: Available | D32: 8 | E32: 0 | F32: 0 | G32: 0 | H32: PACK | I32: 16500 | J32: JPY | K32: 46235 | L32: 3PL-14-2

Sheet Cycle Count Detail
A1: Cycle Count Detail
A2: A separate physical-count source at an overlapping location; review granularity before including it with ERP stock.
A7: Item Number | B7: Storage Location | C7: Stock Status | D7: Physical Qty | E7: Blocked | F7: QI | G7: Damaged | H7: Base UoM | I7: Unit Cost | J7: Currency | K7: Stocktake Date | L7: Serial Batch
A8: EL-1001 | B8: DC-NJ | C8: Counted | D8: 30 | E8: 0 | F8: 0 | G8: 0 | H8: EA | I8: 310 | J8: USD | K8: 46234 | L8: CC-1000
A9: EL-1002 | B9: DC-NJ | C9: Counted | D9: 53 | E9: 0 | F9: 0 | G9: 0 | H9: EA | I9: 420 | J9: USD | K9: 46234 | L9: CC-1001
A10: EL-2001 | B10: DC-NJ | C10: Counted | D10: 76 | E10: 0 | F10: 0 | G10: 0 | H10: EA | I10: 735 | J10: USD | K10: 46234 | L10: CC-1002
A11: EL-2002 | B11: DC-NJ | C11: Counted | D11: 99 | E11: 0 | F11: 0 | G11: 0 | H11: EA | I11: 310 | J11: USD | K11: 46234 | L11: CC-1003
A12: AU-3001 | B12: DC-NJ | C12: Counted | D12: 32 | E12: 0 | F12: 0 | G12: 0 | H12: EA | I12: 86 | J12: USD | K12: 46234 | L12: CC-1004
A13: AU-3002 | B13: DC-NJ | C13: Counted | D13: 55 | E13: 0 | F13: 0 | G13: 0 | H13: EA | I13: 44 | J13: USD | K13: 46234 | L13: CC-1005
A14: GM-4001 | B14: DC-NJ | C14: Counted | D14: 78 | E14: 0 | F14: 0 | G14: 0 | H14: EA | I14: 63 | J14: USD | K14: 46234 | L14: CC-1006
A15: GM-4002 | B15: DC-NJ | C15: Counted | D15: 101 | E15: 0 | F15: 0 | G15: 0 | H15: EA | I15: 31 | J15: USD | K15: 46234 | L15: CC-1007
A16: HM-5001 | B16: DC-NJ | C16: Counted | D16: 34 | E16: 0 | F16: 0 | G16: 0 | H16: EA | I16: 57 | J16: USD | K16: 46234 | L16: CC-1008
A17: HM-5002 | B17: DC-NJ | C17: Counted | D17: 57 | E17: 0 | F17: 0 | G17: 0 | H17: EA | I17: 71 | J17: USD | K17: 46234 | L17: CC-1009
A18: AC-6001 | B18: DC-NJ | C18: Counted | D18: 80 | E18: 0 | F18: 0 | G18: 0 | H18: EA | I18: 14 | J18: EUR | K18: 46234 | L18: CC-1010
A19: AC-6002 | B19: DC-NJ | C19: Counted | D19: 103 | E19: 0 | F19: 0 | G19: 0 | H19: EA | I19: 4.2 | J19: EUR | K19: 46234 | L19: CC-1011
... A21: OF-7002 | B21: DC-NJ | C21: Counted | D21: 59 | E21: 0 | F21: 0 | G21: 0 | H21: EA | I21: 16500 | J21: JPY | K21: 46234 | L21: CC-1013

Sheet Wholesale Consignment
A1: Wholesale Consignment Inventory
A2: Vendor-owned stock at a shared facility. Use the dataset-role and inclusion controls deliberately.
A5: SKU | B5: Warehouse | C5: Inventory Status | D5: On Hand | E5: Reserved Qty | F5: Hold | G5: Damaged Quantity | H5: UOM | I5: Cost Per Unit | J5: Local Currency | K5: Inventory Date | L5: Batch
A6: EL-1001 | B6: 3PL-WEST | C6: Vendor Owned | D6: 7 | E6: 2 | F6: 0 | G6: 0 | H6: EA | I6: 310 | J6: USD | K6: 46235 | L6: CONS-200
A7: EL-1002 | B7: 3PL-WEST | C7: Vendor Owned | D7: 20 | E7: 0 | F7: 0 | G7: 0 | H7: EA | I7: 420 | J7: USD | K7: 46235 | L7: CONS-201
A8: EL-2001 | B8: 3PL-WEST | C8: Vendor Owned | D8: 33 | E8: 0 | F8: 0 | G8: 0 | H8: EA | I8: 735 | J8: USD | K8: 46235 | L8: CONS-202
A9: EL-2002 | B9: 3PL-WEST | C9: Vendor Owned | D9: 46 | E9: 0 | F9: 0 | G9: 0 | H9: EA | I9: 310 | J9: USD | K9: 46235 | L9: CONS-203
A10: AU-3001 | B10: 3PL-WEST | C10: Vendor Owned | D10: 15 | E10: 0 | F10: 0 | G10: 0 | H10: EA | I10: 86 | J10: USD | K10: 46235 | L10: CONS-204
A11: AU-3002 | B11: 3PL-WEST | C11: Vendor Owned | D11: 28 | E11: 0 | F11: 0 | G11: 0 | H11: EA | I11: 44 | J11: USD | K11: 46235 | L11: CONS-205
A12: GM-4001 | B12: 3PL-WEST | C12: Vendor Owned | D12: 41 | E12: 2 | F12: 0 | G12: 0 | H12: EA | I12: 63 | J12: USD | K12: 46235 | L12: CONS-206
A13: GM-4002 | B13: 3PL-WEST | C13: Vendor Owned | D13: 10 | E13: 0 | F13: 0 | G13: 0 | H13: EA | I13: 31 | J13: USD | K13: 46235 | L13: CONS-207
A14: HM-5001 | B14: 3PL-WEST | C14: Vendor Owned | D14: 23 | E14: 0 | F14: 0 | G14: 0 | H14: EA | I14: 57 | J14: USD | K14: 46235 | L14: CONS-208
A15: HM-5002 | B15: 3PL-WEST | C15: Vendor Owned | D15: 36 | E15: 0 | F15: 0 | G15: 0 | H15: EA | I15: 71 | J15: USD | K15: 46235 | L15: CONS-209
A16: AC-6001 | B16: 3PL-WEST | C16: Vendor Owned | D16: 49 | E16: 0 | F16: 0 | G16: 0 | H16: EA | I16: 14 | J16: EUR | K16: 46235 | L16: CONS-210
A17: AC-6002 | B17: 3PL-WEST | C17: Vendor Owned | D17: 18 | E17: 0 | F17: 0 | G17: 0 | H17: EA | I17: 4.2 | J17: EUR | K17: 46235 | L17: CONS-211
... A19: OF-7002 | B19: 3PL-WEST | C19: Vendor Owned | D19: 44 | E19: 0 | F19: 0 | G19: 0 | H19: EA | I19: 16500 | J19: JPY | K19: 46235 | L19: CONS-213

Sheet Monthly Sell Through
A1: Monthly Sell-Through History
A2: Eighteen months of demand with aliases, seasonality, multiple channels, formulas, and one valid negative return.
A4: Fiscal Month End | B4: SKU / Style | C4: Sales Channel | D4: Gross Units | E4: Returns Units | F4: Avg Net Price USD | G4: Net Demand Units Helper
A5: 45716 | B5: N-X1-128 | C5: Retail | D5: 38 | E5: 0 | F5: 18 | G5: =D5-E5 -> 38
A6: 45716 | B6: EL-1002 | C6: Ecommerce | D6: 57 | E6: 1 | F6: 25.5 | G6: =D6-E6 -> 56
A7: 45716 | B7: EL-2001 | C7: Wholesale | D7: 76 | E7: 2 | F7: 33 | G7: =D7-E7 -> 74
A8: 45716 | B8: EL-2002 | C8: Retail | D8: 95 | E8: 3 | F8: 40.5 | G8: =D8-E8 -> 92
A9: 45716 | B9: ORB-ANC | C9: Ecommerce | D9: 114 | E9: 4 | F9: 48 | G9: =D9-E9 -> 110
A10: 45716 | B10: AU-3002 | C10: Wholesale | D10: 133 | E10: 5 | F10: 55.5 | G10: =D10-E10 -> 128
A11: 45716 | B11: GM-4001 | C11: Retail | D11: 152 | E11: 6 | F11: 63 | G11: =D11-E11 -> 146
A12: 45716 | B12: GM-4002 | C12: Ecommerce | D12: 171 | E12: 7 | F12: 70.5 | G12: =D12-E12 -> 164
A13: 45716 | B13: HALO-SPK | C13: Wholesale | D13: 190 | E13: 8 | F13: 78 | G13: =D13-E13 -> 182
A14: 45716 | B14: HM-5002 | C14: Retail | D14: 39 | E14: 0 | F14: 85.5 | G14: =D14-E14 -> 39
A15: 45716 | B15: AC-6001 | C15: Ecommerce | D15: 58 | E15: 1 | F15: 93 | G15: =D15-E15 -> 57
A16: 45716 | B16: AC-6002 | C16: Wholesale | D16: 77 | E16: 2 | F16: 100.5 | G16: =D16-E16 -> 75
... A256: 46234 | B256: OF-7002 | C256: Ecommerce | D256: 132 | E256: 3 | F256: 115.5 | G256: =D256-E256 -> 129

Sheet Open Procurement
A1: Open Procurement Commitments
A2: Open POs use mixed currencies and UOMs. PO-CHF-BLOCK intentionally lacks an FX rate.
A5: Purchase Order | B5: Client Item | C5: Ship From | D5: Ship To | E5: Open Quantity | F5: Order UOM | G5: Expected Receipt | H5: PO Status | I5: PO Unit Price | J5: PO Currency
A6: PO-20260800 | B6: EL-1001 | C6: Shenzhen | D6: DC-NJ | E6: 3 | F6: CS | G6: 46242 | H6: Open | I6: 285.2 | J6: USD
A7: PO-20260801 | B7: N-X1-128 | C7: Shenzhen | D7: DC-TX | E7: 4 | F7: EA | G7: 46245 | H7: Approved | I7: 294.5 | J7: USD
A8: PO-20260802 | B8: EL-1002 | C8: Monterrey | D8: DC-NJ | E8: 4 | F8: EA | G8: 46243 | H8: Approved | I8: 386.4 | J8: USD
A9: PO-20260803 | B9: N-X1-256 | C9: Monterrey | D9: DC-TX | E9: 5 | F9: EA | G9: 46246 | H9: In Transit | I9: 399 | J9: USD
A10: PO-20260804 | B10: EL-2001 | C10: Rotterdam | D10: DC-NJ | E10: 5 | F10: EA | G10: 46244 | H10: In Transit | I10: 676.2 | J10: USD
A11: PO-20260805 | B11: A14-LT | C11: Rotterdam | D11: DC-TX | E11: 6 | F11: CS | G11: 46247 | H11: Supplier Delay | I11: 698.25 | J11: USD
A12: PO-20260806 | B12: EL-2002 | C12: Shenzhen | D12: DC-NJ | E12: 6 | F12: CS | G12: 46245 | H12: Supplier Delay | I12: 285.2 | J12: USD
A13: PO-20260807 | B13: AT-11 | C13: Shenzhen | D13: DC-TX | E13: 7 | F13: EA | G13: 46248 | H13: Open | I13: 294.5 | J13: USD
A14: PO-20260808 | B14: AU-3001 | C14: Monterrey | D14: DC-NJ | E14: 7 | F14: EA | G14: 46246 | H14: Open | I14: 79.12 | J14: USD
A15: PO-20260809 | B15: ORB-ANC | C15: Monterrey | D15: DC-TX | E15: 8 | F15: EA | G15: 46249 | H15: Approved | I15: 81.7 | J15: USD
A16: PO-20260810 | B16: AU-3002 | C16: Rotterdam | D16: DC-NJ | E16: 8 | F16: EA | G16: 46247 | H16: Approved | I16: 40.48 | J16: USD
A17: PO-20260811 | B17: PULSE-BUD | C17: Rotterdam | D17: DC-TX | E17: 9 | F17: CS | G17: 46250 | H17: In Transit | I17: 41.8 | J17: USD
... A34: PO-CHF-BLOCK | B34: GM-4002 | C34: Zurich | D34: DC-NJ | E34: 40 | F34: EA | G34: 46252 | H34: Open | I34: 27 | J34: CHF

Sheet Network Transfers
A1: Network Transfer Pipeline
A2: Transfers include in-transit, delayed, and customs-held movements across the six analysis locations.
A4: Transfer ID | B4: Material | C4: From Site | D4: To Site | E4: In Transit Qty | F4: Qty UOM | G4: ETA | H4: Movement Status | I4: Declared Cost | J4: Currency
A5: TR-8800 | B5: EL-1001 | C5: DC-NJ | D5: NYC-01 | E5: 8 | F5: EA | G5: 46239 | H5: Customs Hold | I5: 310 | J5: USD
A6: TR-8801 | B6: EL-1002 | C6: DC-TX | D6: CHI-02 | E6: 15 | F6: EA | G6: 46240 | H6: In Transit | I6: 420 | J6: USD
A7: TR-8802 | B7: EL-2001 | C7: DC-NJ | D7: NYC-01 | E7: 22 | F7: EA | G7: 46241 | H7: In Transit | I7: 735 | J7: USD
A8: TR-8803 | B8: EL-2002 | C8: DC-TX | D8: CHI-02 | E8: 29 | F8: EA | G8: 46242 | H8: In Transit | I8: 310 | J8: USD
A9: TR-8804 | B9: AU-3001 | C9: DC-NJ | D9: NYC-01 | E9: 36 | F9: EA | G9: 46243 | H9: In Transit | I9: 86 | J9: USD
A10: TR-8805 | B10: AU-3002 | C10: DC-TX | D10: CHI-02 | E10: 43 | F10: EA | G10: 46244 | H10: Delayed | I10: 44 | J10: USD
A11: TR-8806 | B11: GM-4001 | C11: DC-NJ | D11: NYC-01 | E11: 50 | F11: EA | G11: 46245 | H11: In Transit | I11: 63 | J11: USD
A12: TR-8807 | B12: GM-4002 | C12: DC-TX | D12: CHI-02 | E12: 57 | F12: EA | G12: 46246 | H12: Customs Hold | I12: 31 | J12: USD
A13: TR-8808 | B13: HM-5001 | C13: DC-NJ | D13: NYC-01 | E13: 9 | F13: EA | G13: 46247 | H13: In Transit | I13: 57 | J13: USD
A14: TR-8809 | B14: HM-5002 | C14: DC-TX | D14: CHI-02 | E14: 16 | F14: EA | G14: 46248 | H14: In Transit | I14: 71 | J14: USD
A15: TR-8810 | B15: AC-6001 | C15: DC-NJ | D15: NYC-01 | E15: 23 | F15: EA | G15: 46249 | H15: Delayed | I15: 14 | J15: EUR
A16: TR-8811 | B16: AC-6002 | C16: DC-TX | D16: CHI-02 | E16: 30 | F16: EA | G16: 46250 | H16: In Transit | I16: 4.2 | J16: EUR
... A18: TR-8813 | B18: OF-7002 | C18: DC-TX | D18: CHI-02 | E18: 44 | F18: EA | G18: 46252 | H18: In Transit | I18: 16500 | J18: JPY

Sheet Reference Tables
A1: Reference Tables
A2: Two separate candidate regions share this sheet. Sheet names are supporting evidence only.
A4: Curr | B4: USD per Local Currency | C4: FX Date | E4: Policy Class | F4: Default Lead Time Days | G4: Safety Stock Days | H4: Owner
A5: USD | B5: 1 | C5: 46235 | E5: Mobile | F5: 35 | G5: 21 | H5: Planning
A6: EUR | B6: 1.09 | C6: 46235 | E6: Computing | F6: 42 | G6: 21 | H6: Planning
A7: CAD | B7: 0.73 | C7: 46235 | E7: Audio | F7: 28 | G7: 14 | H7: Category
A8: JPY | B8: 0.0067 | C8: 46235 | E8: Accessories | F8: 24 | G8: 14 | H8: Category
E9: Office | F9: 31 | G9: 18 | H9: Operations

Sheet Test Controls
A1: Test Controls
A2: These checks help confirm that the workbook itself is intact before running the add-in.
A4: Control | B4: Formula / Expected | C4: Purpose
A5: Item rows | B5: =COUNTA('Global Product Register'!A5:A18) -> 14 | C5: Should equal 14 authoritative products
A6: Sales rows | B6: =COUNTA('Monthly Sell Through'!B5:B256) -> 252 | C6: Should equal 252 monthly SKU records
A7: SAP rows | B7: =COUNTA('SAP Distribution Stock'!A6:A35) -> 30 | C7: Includes one exact repeat and one extra batch
A8: Oracle rows | B8: =COUNTA('Oracle Retail Count'!A7:A36) -> 30 | C8: Includes unknown and ambiguous SKU rows
A9: 3PL rows | B9: =COUNTA('3PL External Feed'!A5:A32) -> 28 | C9: Contains CS/PACK conversions
A10: PO rows | B10: =COUNTA('Open Procurement'!A6:A34) -> 29 | C10: Includes the CHF blocker
A11: Transfer rows | B11: =COUNTA('Network Transfers'!A5:A18) -> 14 | C11: Contains delayed/customs-held movements
A12: Workbook intent | B12: Stress test | C12: Do not treat these controls as inventory data

Sheet Regional P and L
A1: Regional Profit & Loss
A2: Unrelated finance data included to test that inventory discovery ignores plausible numeric business tables.
A4: Fiscal Period | B4: Region | C4: Revenue | D4: COGS | E4: Operating Expense | F4: Gross Profit | G4: EBITDA
A5: 45716 | B5: North | C5: 820000 | D5: 490000 | E5: 165000 | F5: =C5-D5 -> 330000 | G5: =F5-E5 -> 165000
A6: 45716 | B6: South | C6: 672400 | D6: 401800 | E6: 135300 | F6: =C6-D6 -> 270600 | G6: =F6-E6 -> 135300
A7: 45716 | B7: West | C7: 557600 | D7: 333200 | E7: 112200 | F7: =C7-D7 -> 224400 | G7: =F7-E7 -> 112200
A8: 45747 | B8: North | C8: 837000 | D8: 499000 | E8: 168500 | F8: =C8-D8 -> 338000 | G8: =F8-E8 -> 169500
A9: 45747 | B9: South | C9: 689400 | D9: 410800 | E9: 138800 | F9: =C9-D9 -> 278600 | G9: =F9-E9 -> 139800
A10: 45747 | B10: West | C10: 574600 | D10: 342200 | E10: 115700 | F10: =C10-D10 -> 232400 | G10: =F10-E10 -> 116700
A11: 45777 | B11: North | C11: 854000 | D11: 508000 | E11: 172000 | F11: =C11-D11 -> 346000 | G11: =F11-E11 -> 174000
A12: 45777 | B12: South | C12: 706400 | D12: 419800 | E12: 142300 | F12: =C12-D12 -> 286600 | G12: =F12-E12 -> 144300
A13: 45777 | B13: West | C13: 591600 | D13: 351200 | E13: 119200 | F13: =C13-D13 -> 240400 | G13: =F13-E13 -> 121200
A14: 45808 | B14: North | C14: 871000 | D14: 517000 | E14: 175500 | F14: =C14-D14 -> 354000 | G14: =F14-E14 -> 178500
A15: 45808 | B15: South | C15: 723400 | D15: 428800 | E15: 145800 | F15: =C15-D15 -> 294600 | G15: =F15-E15 -> 148800
A16: 45808 | B16: West | C16: 608600 | D16: 360200 | E16: 122700 | F16: =C16-D16 -> 248400 | G16: =F16-E16 -> 125700
... A31: 45961 | B31: West | C31: 693600 | D31: 405200 | E31: 140200 | F31: =C31-D31 -> 288400 | G31: =F31-E31 -> 148200

Sheet Treasury Cash Forecast
A1: Treasury Cash Forecast
A2: Formula-driven cash planning data that must not be classified as inventory, sales, supply, or FX.
A5: Week Ending | B5: Opening Cash | C5: Net Cash Flow | D5: Closing Cash | E5: Minimum Buffer | F5: Owner
A6: 46237 | B6: 125000 | C6: 98000 | D6: =B6+C6 -> 223000 | E6: 90000 | F6: Treasury
A7: 46244 | B7: 126500 | C7: 107700 | D7: =B7+C7 -> 234200 | E7: 90000 | F7: Treasury
A8: 46251 | B8: 128000 | C8: 117400 | D8: =B8+C8 -> 245400 | E8: 90000 | F8: Treasury
A9: 46258 | B9: 129500 | C9: 127100 | D9: =B9+C9 -> 256600 | E9: 90000 | F9: Treasury
A10: 46265 | B10: 131000 | C10: 136800 | D10: =B10+C10 -> 267800 | E10: 90000 | F10: Treasury
A11: 46272 | B11: 132500 | C11: 104500 | D11: =B11+C11 -> 237000 | E11: 90000 | F11: Treasury
A12: 46279 | B12: 134000 | C12: 114200 | D12: =B12+C12 -> 248200 | E12: 90000 | F12: Treasury
A13: 46286 | B13: 135500 | C13: 123900 | D13: =B13+C13 -> 259400 | E13: 90000 | F13: Treasury
A14: 46293 | B14: 137000 | C14: 133600 | D14: =B14+C14 -> 270600 | E14: 90000 | F14: Treasury
A15: 46300 | B15: 138500 | C15: 101300 | D15: =B15+C15 -> 239800 | E15: 90000 | F15: Treasury
A16: 46307 | B16: 140000 | C16: 111000 | D16: =B16+C16 -> 251000 | E16: 90000 | F16: Treasury
A17: 46314 | B17: 141500 | C17: 120700 | D17: =B17+C17 -> 262200 | E17: 90000 | F17: Treasury

Sheet Journal Export
A1: General Ledger Journal Export
A2: A large unrelated transaction table with dates, codes, statuses, and currency fields.
A4: Journal ID | B4: Posting Date | C4: Account | D4: Narrative | E4: Debit | F4: Credit | G4: Ledger Currency | H4: Approval Status
A5: JE-90000 | B5: 46204 | C5: 400100 | D5: Sales accrual | E5: 1000 | F5: 0 | G5: USD | H5: Posted
A6: JE-90001 | B6: 46205 | C6: 500200 | D6: Freight | E6: 0 | F6: 1293 | G6: USD | H6: Approved
A7: JE-90002 | B7: 46206 | C7: 610300 | D7: Payroll | E7: 1634 | F7: 0 | G7: USD | H7: Approved
A8: JE-90003 | B8: 46207 | C8: 720400 | D8: Marketing | E8: 0 | F8: 1879 | G8: USD | H8: Approved
A9: JE-90004 | B9: 46208 | C9: 130500 | D9: Receivable | E9: 2268 | F9: 0 | G9: USD | H9: Posted
A10: JE-90005 | B10: 46209 | C10: 400100 | D10: Sales accrual | E10: 0 | F10: 2465 | G10: USD | H10: Approved
A11: JE-90006 | B11: 46210 | C11: 500200 | D11: Freight | E11: 2902 | F11: 0 | G11: USD | H11: Approved
A12: JE-90007 | B12: 46211 | C12: 610300 | D12: Payroll | E12: 0 | F12: 3051 | G12: USD | H12: Approved
A13: JE-90008 | B13: 46212 | C13: 720400 | D13: Marketing | E13: 3536 | F13: 0 | G13: USD | H13: Posted
A14: JE-90009 | B14: 46213 | C14: 130500 | D14: Receivable | E14: 0 | F14: 3637 | G14: USD | H14: Approved
A15: JE-90010 | B15: 46214 | C15: 400100 | D15: Sales accrual | E15: 4170 | F15: 0 | G15: USD | H15: Approved
A16: JE-90011 | B16: 46215 | C16: 500200 | D16: Freight | E16: 0 | F16: 4223 | G16: USD | H16: Approved
... A34: JE-90029 | B34: 46205 | C34: 130500 | D34: Receivable | E34: 0 | F34: 9497 | G34: USD | H34: Approved

Sheet Marketing Commitments
A1: Marketing Commitments
A2: Unrelated campaign budgets add more realistic workbook noise and varied data types.
A6: Campaign | B6: Channel Group | C6: Region | D6: Committed Spend | E6: Forecast Confidence | F6: Launch Date | G6: Status
A7: CMP-700 | B7: Search | C7: North | D7: 12000 | E7: 0.72 | F7: 46235 | G7: Planned
A8: CMP-701 | B8: Social | C8: South | D8: 13700 | E8: 0.755 | F8: 46236 | G8: Approved
A9: CMP-702 | B9: Retail Media | C9: West | D9: 15400 | E9: 0.79 | F9: 46237 | G9: Approved
A10: CMP-703 | B10: Events | C10: North | D10: 17100 | E10: 0.825 | F10: 46238 | G10: Approved
A11: CMP-704 | B11: Search | C11: South | D11: 18800 | E11: 0.86 | F11: 46239 | G11: Approved
A12: CMP-705 | B12: Social | C12: West | D12: 20500 | E12: 0.895 | F12: 46240 | G12: Planned
A13: CMP-706 | B13: Retail Media | C13: North | D13: 22200 | E13: 0.93 | F13: 46241 | G13: Approved
A14: CMP-707 | B14: Events | C14: South | D14: 23900 | E14: 0.965 | F14: 46242 | G14: Approved
A15: CMP-708 | B15: Search | C15: West | D15: 25600 | E15: 1 | F15: 46243 | G15: Approved
A16: CMP-709 | B16: Social | C16: North | D16: 27300 | E16: 1.035 | F16: 46244 | G16: Approved
A17: CMP-710 | B17: Retail Media | C17: South | D17: 29000 | E17: 0.72 | F17: 46245 | G17: Planned
A18: CMP-711 | B18: Events | C18: West | D18: 30700 | E18: 0.755 | F18: 46246 | G18: Approved
... A26: CMP-719 | B26: Events | C26: South | D26: 16300 | E26: 1.035 | F26: 46254 | G26: Approved
